Workbook

Sheet Supuestos
A1: Bolivia: Servicio Ampliado del FMI (SAF) 2026-2029. Supuestos y tramos
A2: Azul = insumo editable · Negro = fórmula · Amarillo = supuesto clave. Montos en millones de DEG salvo indicación.
A4: Parámetro | C4: Valor | D4: Nota / fuente
A5: Cuota de Bolivia en el FMI | C5: 240.1 | D5: DEG mm. Ficha del país, FMI
A6: Acceso total aprobado | C6: 1369 | D6: DEG mm = 570% de la cuota. Directorio, 2-oct-2026
A7: Tipo de cambio USD por DEG | C7: 1.3536195 | D7: Implícito en el primer desembolso: USD 211,3 mm = DEG 156,1 mm (BCB, 6-oct-2026)
A8: Tasa de interés del DEG | C8: 0.0287 | D8: Supuesto: implícita en la tasa de 3,47% informada, menos el margen de 60 pb. Se mantiene constante
A9: Margen sobre la tasa del DEG | C9: 0.006 | D9: 60 pb desde la reforma de nov-2024
A10: Umbral de sobrecargo por nivel | C10: 3 | D10: 300% de la cuota (reforma 2024)
A11: Sobrecargo por nivel | C11: 0.02 | D11: 200 pb sobre el crédito que excede el umbral
A12: Meses sobre el umbral para el sobrecargo por tiempo (SAF) | C12: 51 | D12: 51 meses en el SAF (36 en otros servicios)
A13: Sobrecargo por tiempo | C13: 0.0075 | D13: 75 pb adicionales (reforma 2024)
A14: Cargo por servicio (sobre cada desembolso) | C14: 0.005 | D14: 50 pb por giro
A15: Inicio de repago tras cada desembolso | C15: 54 | D15: 4,5 años
A16: Último repago tras cada desembolso | C16: 120 | D16: 10 años
A17: Número de cuotas semestrales iguales | C17: 12 | D17: Repago estándar del SAF
A18: Umbral de sobrecargo en DEG | C18: =Supuestos!$C$10*Supuestos!$C$5 -> 720.3
A19: Tasa de cargo básica (DEG + margen) | C19: =Supuestos!$C$8+Supuestos!$C$9 -> 0.0347
A21: Tramos del acuerdo (fechas y montos editables)
A22: # | B22: Evento | C22: Fecha | D22: Monto (DEG mm) | E22: Monto (USD mm) | F22: % de la cuota | G22: Acumulado (DEG mm) | H22: Acumulado (% cuota) | I22: Índice de mes | J22: Primer repago | K22: Último repago | L22: Cuota semestral (DEG mm)
A23: 1 | B23: Aprobación del Directorio | C23: 46296 | D23: 156.1 | E23: =D23*Supuestos!$C$7 -> 211.3 | F23: =D23/Supuestos!$C$5 -> 0.65014577 | G23: =SUM(D$23:D23) -> 156.1 | H23: =G23/Supuestos!$C$5 -> 0.65014577 | I23: =YEAR(C23)*12+MONTH(C23) -> 24322 | J23: =EDATE(C23,Supuestos!$C$15) -> 47939 | K23: =EDATE(C23,Supuestos!$C$16) -> 49949 | L23: =D23/Supuestos!$C$17 -> 13.008333
A24: 2 | B24: 1ª revisión | C24: 46357 | D24: 156 | E24: =D24*Supuestos!$C$7 -> 211.16464 | F24: =D24/Supuestos!$C$5 -> 0.64972928 | G24: =SUM(D$23:D24) -> 312.1 | H24: =G24/Supuestos!$C$5 -> 1.2998751 | I24: =YEAR(C24)*12+MONTH(C24) -> 24324 | J24: =EDATE(C24,Supuestos!$C$15) -> 48000 | K24: =EDATE(C24,Supuestos!$C$16) -> 50010 | L24: =D24/Supuestos!$C$17 -> 13
A25: 3 | B25: 2ª revisión | C25: 46447 | D25: 96.08 | E25: =D25*Supuestos!$C$7 -> 130.05576 | F25: =D25/Supuestos!$C$5 -> 0.4001666 | G25: =SUM(D$23:D25) -> 408.18 | H25: =G25/Supuestos!$C$5 -> 1.7000416 | I25: =YEAR(C25)*12+MONTH(C25) -> 24327 | J25: =EDATE(C25,Supuestos!$C$15) -> 48092 | K25: =EDATE(C25,Supuestos!$C$16) -> 50100 | L25: =D25/Supuestos!$C$17 -> 8.0066667
A26: 4 | B26: 3ª revisión | C26: 46539 | D26: 96.08 | E26: =D26*Supuestos!$C$7 -> 130.05576 | F26: =D26/Supuestos!$C$5 -> 0.4001666 | G26: =SUM(D$23:D26) -> 504.26 | H26: =G26/Supuestos!$C$5 -> 2.1002082 | I26: =YEAR(C26)*12+MONTH(C26) -> 24330 | J26: =EDATE(C26,Supuestos!$C$15) -> 48183 | K26: =EDATE(C26,Supuestos!$C$16) -> 50192 | L26: =D26/Supuestos!$C$17 -> 8.0066667
A27: 5 | B27: 4ª revisión | C27: 46631 | D27: 96.08 | E27: =D27*Supuestos!$C$7 -> 130.05576 | F27: =D27/Supuestos!$C$5 -> 0.4001666 | G27: =SUM(D$23:D27) -> 600.34 | H27: =G27/Supuestos!$C$5 -> 2.5003748 | I27: =YEAR(C27)*12+MONTH(C27) -> 24333 | J27: =EDATE(C27,Supuestos!$C$15) -> 48274 | K27: =EDATE(C27,Supuestos!$C$16) -> 50284 | L27: =D27/Supuestos!$C$17 -> 8.0066667
A28: 6 | B28: 5ª revisión | C28: 46722 | D28: 96.08 | E28: =D28*Supuestos!$C$7 -> 130.05576 | F28: =D28/Supuestos!$C$5 -> 0.4001666 | G28: =SUM(D$23:D28) -> 696.42 | H28: =G28/Supuestos!$C$5 -> 2.9005414 | I28: =YEAR(C28)*12+MONTH(C28) -> 24336 | J28: =EDATE(C28,Supuestos!$C$15) -> 48366 | K28: =EDATE(C28,Supuestos!$C$16) -> 50375 | L28: =D28/Supuestos!$C$17 -> 8.0066667
A29: 7 | B29: 6ª revisión | C29: 46813 | D29: 96.08 | E29: =D29*Supuestos!$C$7 -> 130.05576 | F29: =D29/Supuestos!$C$5 -> 0.4001666 | G29: =SUM(D$23:D29) -> 792.5 | H29: =G29/Supuestos!$C$5 -> 3.300708 | I29: =YEAR(C29)*12+MONTH(C29) -> 24339 | J29: =EDATE(C29,Supuestos!$C$15) -> 48458 | K29: =EDATE(C29,Supuestos!$C$16) -> 50465 | L29: =D29/Supuestos!$C$17 -> 8.0066667
A30: 8 | B30: 7ª revisión | C30: 46905 | D30: 96.08 | E30: =D30*Supuestos!$C$7 -> 130.05576 | F30: =D30/Supuestos!$C$5 -> 0.4001666 | G30: =SUM(D$23:D30) -> 888.58 | H30: =G30/Supuestos!$C$5 -> 3.7008746 | I30: =YEAR(C30)*12+MONTH(C30) -> 24342 | J30: =EDATE(C30,Supuestos!$C$15) -> 48549 | K30: =EDATE(C30,Supuestos!$C$16) -> 50557 | L30: =D30/Supuestos!$C$17 -> 8.0066667
A31: 9 | B31: 8ª revisión | C31: 46997 | D31: 96.08 | E31: =D31*Supuestos!$C$7 -> 130.05576 | F31: =D31/Supuestos!$C$5 -> 0.4001666 | G31: =SUM(D$23:D31) -> 984.66 | H31: =G31/Supuestos!$C$5 -> 4.1010412 | I31: =YEAR(C31)*12+MONTH(C31) -> 24345 | J31: =EDATE(C31,Supuestos!$C$15) -> 48639 | K31: =EDATE(C31,Supuestos!$C$16) -> 50649 | L31: =D31/Supuestos!$C$17 -> 8.0066667
A32: 10 | B32: 9ª revisión | C32: 47088 | D32: 96.08 | E32: =D32*Supuestos!$C$7 -> 130.05576 | F32: =D32/Supuestos!$C$5 -> 0.4001666 | G32: =SUM(D$23:D32) -> 1080.74 | H32: =G32/Supuestos!$C$5 -> 4.5012078 | I32: =YEAR(C32)*12+MONTH(C32) -> 24348 | J32: =EDATE(C32,Supuestos!$C$15) -> 48731 | K32: =EDATE(C32,Supuestos!$C$16) -> 50740 | L32: =D32/Supuestos!$C$17 -> 8.0066667
A33: 11 | B33: 10ª revisión | C33: 47178 | D33: 96.08 | E33: =D33*Supuestos!$C$7 -> 130.05576 | F33: =D33/Supuestos!$C$5 -> 0.4001666 | G33: =SUM(D$23:D33) -> 1176.82 | H33: =G33/Supuestos!$C$5 -> 4.9013744 | I33: =YEAR(C33)*12+MONTH(C33) -> 24351 | J33: =EDATE(C33,Supuestos!$C$15) -> 48823 | K33: =EDATE(C33,Supuestos!$C$16) -> 50830 | L33: =D33/Supuestos!$C$17 -> 8.0066667
A34: 12 | B34: 11ª revisión | C34: 47270 | D34: 96.08 | E34: =D34*Supuestos!$C$7 -> 130.05576 | F34: =D34/Supuestos!$C$5 -> 0.4001666 | G34: =SUM(D$23:D34) -> 1272.9 | H34: =G34/Supuestos!$C$5 -> 5.301541 | I34: =YEAR(C34)*12+MONTH(C34) -> 24354 | J34: =EDATE(C34,Supuestos!$C$15) -> 48914 | K34: =EDATE(C34,Supuestos!$C$16) -> 50922 | L34: =D34/Supuestos!$C$17 -> 8.0066667
A35: 13 | B35: 12ª revisión | C35: 47362 | D35: =Supuestos!$C$6-SUM(D23:D34) -> 96.1 | E35: =D35*Supuestos!$C$7 -> 130.08283 | F35: =D35/Supuestos!$C$5 -> 0.4002499 | G35: =SUM(D$23:D35) -> 1369 | H35: =G35/Supuestos!$C$5 -> 5.7017909 | I35: =YEAR(C35)*12+MONTH(C35) -> 24357 | J35: =EDATE(C35,Supuestos!$C$15) -> 49004 | K35: =EDATE(C35,Supuestos!$C$16) -> 51014 | L35: =D35/Supuestos!$C$17 -> 8.0083333
B36: Total | D36: =SUM(D23:D35) -> 1369 | E36: =SUM(E23:E35) -> 1853.1051 | F36: =SUM(F23:F35) -> 5.7017909
B37: Control: total = acceso | D37: =IF(ABS(D36-Supuestos!$C$6)<0.001,"OK","REVISAR") -> OK
A39: Fechas y montos de las revisiones 1 a 12: supuesto. El FMI no publicó el calendario en las fuentes consultadas. Los supuestos: (i) el primer tramo de DEG 156,1 mm es dato (BCB); (ii) un segundo tramo de monto similar en nov-dic 2026, según el ministro de Economía; (iii) desde 2027, revisiones trimestrales con montos iguales que completan DEG 1.369 mm, en un acuerdo de 36 meses (oct-2026 a sep-2029). El último tramo es residual, así que cualquier cambio en los montos mantiene el total.

Sheet Mensual
A1: Cronograma mensual (DEG mm)
A2: Los cargos se devengan sobre el saldo a fin del mes anterior; el FMI los liquida trimestralmente. Repago: 12 cuotas semestrales iguales de cada tramo, entre los meses 54 y 120 posteriores al giro.
A4: Mes | B4: Índice | C4: Año | D4: Desembolso | E4: Repago de capital | F4: Saldo adeudado | G4: Saldo (% cuota) | H4: Exceso sobre umbral (saldo previo) | I4: Meses consecutivos sobre umbral | J4: Cargo básico | K4: Sobrecargo por nivel | L4: Sobrecargo por tiempo | M4: Cargo por servicio | N4: Cargos totales | O4: Servicio total (capital + cargos)
A5: =Supuestos!$C$23 -> 46296 | B5: =YEAR(A5)*12+MONTH(A5) -> 24322 | C5: =YEAR(A5) -> 2026 | D5: =SUMIF(Supuestos!$I$23:$I$35,B5,Supuestos!$D$23:$D$35) -> 156.1 | E5: =SUMPRODUCT(Supuestos!$D$23:$D$35*((B5-Supuestos!$I$23:$I$35)>=Supuestos!$C$15)*((B5-Supuestos!$I$23:$I$35)<=Supuestos!$C$16)*(MOD((B5-Supuestos!$I$23:$I$35)-Supuestos!$C$15,6)=0))/Supuestos!$C$17 -> 0 | F5: =0+D5-E5 -> 156.1 | G5: =F5/Supuestos!$C$5 -> 0.65014577 | H5: =MAX(0,0-Supuestos!$C$18) -> 0 | I5: =IF(F5>Supuestos!$C$18,0+1,0) -> 0 | J5: =0*Supuestos!$C$19/12 -> 0 | K5: =H5*Supuestos!$C$11/12 -> 0 | L5: =IF(0>Supuestos!$C$12,H5*Supuestos!$C$13/12,0) -> 0 | M5: =D5*Supuestos!$C$14 -> 0.7805 | N5: =SUM(J5:M5) -> 0.7805 | O5: =E5+N5 -> 0.7805
A6: =EDATE(A5,1) -> 46327 | B6: =YEAR(A6)*12+MONTH(A6) -> 24323 | C6: =YEAR(A6) -> 2026 | D6: =SUMIF(Supuestos!$I$23:$I$35,B6,Supuestos!$D$23:$D$35) -> 0 | E6: =SUMPRODUCT(Supuestos!$D$23:$D$35*((B6-Supuestos!$I$23:$I$35)>=Supuestos!$C$15)*((B6-Supuestos!$I$23:$I$35)<=Supuestos!$C$16)*(MOD((B6-Supuestos!$I$23:$I$35)-Supuestos!$C$15,6)=0))/Supuestos!$C$17 -> 0 | F6: =F5+D6-E6 -> 156.1 | G6: =F6/Supuestos!$C$5 -> 0.65014577 | H6: =MAX(0,F5-Supuestos!$C$18) -> 0 | I6: =IF(F6>Supuestos!$C$18,I5+1,0) -> 0 | J6: =F5*Supuestos!$C$19/12 -> 0.45138917 | K6: =H6*Supuestos!$C$11/12 -> 0 | L6: =IF(I5>Supuestos!$C$12,H6*Supuestos!$C$13/12,0) -> 0 | M6: =D6*Supuestos!$C$14 -> 0 | N6: =SUM(J6:M6) -> 0.45138917 | O6: =E6+N6 -> 0.45138917
A7: =EDATE(A6,1) -> 46357 | B7: =YEAR(A7)*12+MONTH(A7) -> 24324 | C7: =YEAR(A7) -> 2026 | D7: =SUMIF(Supuestos!$I$23:$I$35,B7,Supuestos!$D$23:$D$35) -> 156 | E7: =SUMPRODUCT(Supuestos!$D$23:$D$35*((B7-Supuestos!$I$23:$I$35)>=Supuestos!$C$15)*((B7-Supuestos!$I$23:$I$35)<=Supuestos!$C$16)*(MOD((B7-Supuestos!$I$23:$I$35)-Supuestos!$C$15,6)=0))/Supuestos!$C$17 -> 0 | F7: =F6+D7-E7 -> 312.1 | G7: =F7/Supuestos!$C$5 -> 1.2998751 | H7: =MAX(0,F6-Supuestos!$C$18) -> 0 | I7: =IF(F7>Supuestos!$C$18,I6+1,0) -> 0 | J7: =F6*Supuestos!$C$19/12 -> 0.45138917 | K7: =H7*Supuestos!$C$11/12 -> 0 | L7: =IF(I6>Supuestos!$C$12,H7*Supuestos!$C$13/12,0) -> 0 | M7: =D7*Supuestos!$C$14 -> 0.78 | N7: =SUM(J7:M7) -> 1.2313892 | O7: =E7+N7 -> 1.2313892
A8: =EDATE(A7,1) -> 46388 | B8: =YEAR(A8)*12+MONTH(A8) -> 24325 | C8: =YEAR(A8) -> 2027 | D8: =SUMIF(Supuestos!$I$23:$I$35,B8,Supuestos!$D$23:$D$35) -> 0 | E8: =SUMPRODUCT(Supuestos!$D$23:$D$35*((B8-Supuestos!$I$23:$I$35)>=Supuestos!$C$15)*((B8-Supuestos!$I$23:$I$35)<=Supuestos!$C$16)*(MOD((B8-Supuestos!$I$23:$I$35)-Supuestos!$C$15,6)=0))/Supuestos!$C$17 -> 0 | F8: =F7+D8-E8 -> 312.1 | G8: =F8/Supuestos!$C$5 -> 1.2998751 | H8: =MAX(0,F7-Supuestos!$C$18) -> 0 | I8: =IF(F8>Supuestos!$C$18,I7+1,0) -> 0 | J8: =F7*Supuestos!$C$19/12 -> 0.90248917 | K8: =H8*Supuestos!$C$11/12 -> 0 | L8: =IF(I7>Supuestos!$C$12,H8*Supuestos!$C$13/12,0) -> 0 | M8: =D8*Supuestos!$C$14 -> 0 | N8: =SUM(J8:M8) -> 0.90248917 | O8: =E8+N8 -> 0.90248917
A9: =EDATE(A8,1) -> 46419 | B9: =YEAR(A9)*12+MONTH(A9) -> 24326 | C9: =YEAR(A9) -> 2027 | D9: =SUMIF(Supuestos!$I$23:$I$35,B9,Supuestos!$D$23:$D$35) -> 0 | E9: =SUMPRODUCT(Supuestos!$D$23:$D$35*((B9-Supuestos!$I$23:$I$35)>=Supuestos!$C$15)*((B9-Supuestos!$I$23:$I$35)<=Supuestos!$C$16)*(MOD((B9-Supuestos!$I$23:$I$35)-Supuestos!$C$15,6)=0))/Supuestos!$C$17 -> 0 | F9: =F8+D9-E9 -> 312.1 | G9: =F9/Supuestos!$C$5 -> 1.2998751 | H9: =MAX(0,F8-Supuestos!$C$18) -> 0 | I9: =IF(F9>Supuestos!$C$18,I8+1,0) -> 0 | J9: =F8*Supuestos!$C$19/12 -> 0.90248917 | K9: =H9*Supuestos!$C$11/12 -> 0 | L9: =IF(I8>Supuestos!$C$12,H9*Supuestos!$C$13/12,0) -> 0 | M9: =D9*Supuestos!$C$14 -> 0 | N9: =SUM(J9:M9) -> 0.90248917 | O9: =E9+N9 -> 0.90248917
A10: =EDATE(A9,1) -> 46447 | B10: =YEAR(A10)*12+MONTH(A10) -> 24327 | C10: =YEAR(A10) -> 2027 | D10: =SUMIF(Supuestos!$I$23:$I$35,B10,Supuestos!$D$23:$D$35) -> 96.08 | E10: =SUMPRODUCT(Supuestos!$D$23:$D$35*((B10-Supuestos!$I$23:$I$35)>=Supuestos!$C$15)*((B10-Supuestos!$I$23:$I$35)<=Supuestos!$C$16)*(MOD((B10-Supuestos!$I$23:$I$35)-Supuestos!$C$15,6)=0))/Supuestos!$C$17 -> 0 | F10: =F9+D10-E10 -> 408.18 | G10: =F10/Supuestos!$C$5 -> 1.7000416 | H10: =MAX(0,F9-Supuestos!$C$18) -> 0 | I10: =IF(F10>Supuestos!$C$18,I9+1,0) -> 0 | J10: =F9*Supuestos!$C$19/12 -> 0.90248917 | K10: =H10*Supuestos!$C$11/12 -> 0 | L10: =IF(I9>Supuestos!$C$12,H10*Supuestos!$C$13/12,0) -> 0 | M10: =D10*Supuestos!$C$14 -> 0.4804 | N10: =SUM(J10:M10) -> 1.3828892 | O10: =E10+N10 -> 1.3828892
A11: =EDATE(A10,1) -> 46478 | B11: =YEAR(A11)*12+MONTH(A11) -> 24328 | C11: =YEAR(A11) -> 2027 | D11: =SUMIF(Supuestos!$I$23:$I$35,B11,Supuestos!$D$23:$D$35) -> 0 | E11: =SUMPRODUCT(Supuestos!$D$23:$D$35*((B11-Supuestos!$I$23:$I$35)>=Supuestos!$C$15)*((B11-Supuestos!$I$23:$I$35)<=Supuestos!$C$16)*(MOD((B11-Supuestos!$I$23:$I$35)-Supuestos!$C$15,6)=0))/Supuestos!$C$17 -> 0 | F11: =F10+D11-E11 -> 408.18 | G11: =F11/Supuestos!$C$5 -> 1.7000416 | H11: =MAX(0,F10-Supuestos!$C$18) -> 0 | I11: =IF(F11>Supuestos!$C$18,I10+1,0) -> 0 | J11: =F10*Supuestos!$C$19/12 -> 1.1803205 | K11: =H11*Supuestos!$C$11/12 -> 0 | L11: =IF(I10>Supuestos!$C$12,H11*Supuestos!$C$13/12,0) -> 0 | M11: =D11*Supuestos!$C$14 -> 0 | N11: =SUM(J11:M11) -> 1.1803205 | O11: =E11+N11 -> 1.1803205
A12: =EDATE(A11,1) -> 46508 | B12: =YEAR(A12)*12+MONTH(A12) -> 24329 | C12: =YEAR(A12) -> 2027 | D12: =SUMIF(Supuestos!$I$23:$I$35,B12,Supuestos!$D$23:$D$35) -> 0 | E12: =SUMPRODUCT(Supuestos!$D$23:$D$35*((B12-Supuestos!$I$23:$I$35)>=Supuestos!$C$15)*((B12-Supuestos!$I$23:$I$35)<=Supuestos!$C$16)*(MOD((B12-Supuestos!$I$23:$I$35)-Supuestos!$C$15,6)=0))/Supuestos!$C$17 -> 0 | F12: =F11+D12-E12 -> 408.18 | G12: =F12/Supuestos!$C$5 -> 1.7000416 | H12: =MAX(0,F11-Supuestos!$C$18) -> 0 | I12: =IF(F12>Supuestos!$C$18,I11+1,0) -> 0 | J12: =F11*Supuestos!$C$19/12 -> 1.1803205 | K12: =H12*Supuestos!$C$11/12 -> 0 | L12: =IF(I11>Supuestos!$C$12,H12*Supuestos!$C$13/12,0) -> 0 | M12: =D12*Supuestos!$C$14 -> 0 | N12: =SUM(J12:M12) -> 1.1803205 | O12: =E12+N12 -> 1.1803205
A13: =EDATE(A12,1) -> 46539 | B13: =YEAR(A13)*12+MONTH(A13) -> 24330 | C13: =YEAR(A13) -> 2027 | D13: =SUMIF(Supuestos!$I$23:$I$35,B13,Supuestos!$D$23:$D$35) -> 96.08 | E13: =SUMPRODUCT(Supuestos!$D$23:$D$35*((B13-Supuestos!$I$23:$I$35)>=Supuestos!$C$15)*((B13-Supuestos!$I$23:$I$35)<=Supuestos!$C$16)*(MOD((B13-Supuestos!$I$23:$I$35)-Supuestos!$C$15,6)=0))/Supuestos!$C$17 -> 0 | F13: =F12+D13-E13 -> 504.26 | G13: =F13/Supuestos!$C$5 -> 2.1002082 | H13: =MAX(0,F12-Supuestos!$C$18) -> 0 | I13: =IF(F13>Supuestos!$C$18,I12+1,0) -> 0 | J13: =F12*Supuestos!$C$19/12 -> 1.1803205 | K13: =H13*Supuestos!$C$11/12 -> 0 | L13: =IF(I12>Supuestos!$C$12,H13*Supuestos!$C$13/12,0) -> 0 | M13: =D13*Supuestos!$C$14 -> 0.4804 | N13: =SUM(J13:M13) -> 1.6607205 | O13: =E13+N13 -> 1.6607205
A14: =EDATE(A13,1) -> 46569 | B14: =YEAR(A14)*12+MONTH(A14) -> 24331 | C14: =YEAR(A14) -> 2027 | D14: =SUMIF(Supuestos!$I$23:$I$35,B14,Supuestos!$D$23:$D$35) -> 0 | E14: =SUMPRODUCT(Supuestos!$D$23:$D$35*((B14-Supuestos!$I$23:$I$35)>=Supuestos!$C$15)*((B14-Supuestos!$I$23:$I$35)<=Supuestos!$C$16)*(MOD((B14-Supuestos!$I$23:$I$35)-Supuestos!$C$15,6)=0))/Supuestos!$C$17 -> 0 | F14: =F13+D14-E14 -> 504.26 | G14: =F14/Supuestos!$C$5 -> 2.1002082 | H14: =MAX(0,F13-Supuestos!$C$18) -> 0 | I14: =IF(F14>Supuestos!$C$18,I13+1,0) -> 0 | J14: =F13*Supuestos!$C$19/12 -> 1.4581518 | K14: =H14*Supuestos!$C$11/12 -> 0 | L14: =IF(I13>Supuestos!$C$12,H14*Supuestos!$C$13/12,0) -> 0 | M14: =D14*Supuestos!$C$14 -> 0 | N14: =SUM(J14:M14) -> 1.4581518 | O14: =E14+N14 -> 1.4581518
A15: =EDATE(A14,1) -> 46600 | B15: =YEAR(A15)*12+MONTH(A15) -> 24332 | C15: =YEAR(A15) -> 2027 | D15: =SUMIF(Supuestos!$I$23:$I$35,B15,Supuestos!$D$23:$D$35) -> 0 | E15: =SUMPRODUCT(Supuestos!$D$23:$D$35*((B15-Supuestos!$I$23:$I$35)>=Supuestos!$C$15)*((B15-Supuestos!$I$23:$I$35)<=Supuestos!$C$16)*(MOD((B15-Supuestos!$I$23:$I$35)-Supuestos!$C$15,6)=0))/Supuestos!$C$17 -> 0 | F15: =F14+D15-E15 -> 504.26 | G15: =F15/Supuestos!$C$5 -> 2.1002082 | H15: =MAX(0,F14-Supuestos!$C$18) -> 0 | I15: =IF(F15>Supuestos!$C$18,I14+1,0) -> 0 | J15: =F14*Supuestos!$C$19/12 -> 1.4581518 | K15: =H15*Supuestos!$C$11/12 -> 0 | L15: =IF(I14>Supuestos!$C$12,H15*Supuestos!$C$13/12,0) -> 0 | M15: =D15*Supuestos!$C$14 -> 0 | N15: =SUM(J15:M15) -> 1.4581518 | O15: =E15+N15 -> 1.4581518
A16: =EDATE(A15,1) -> 46631 | B16: =YEAR(A16)*12+MONTH(A16) -> 24333 | C16: =YEAR(A16) -> 2027 | D16: =SUMIF(Supuestos!$I$23:$I$35,B16,Supuestos!$D$23:$D$35) -> 96.08 | E16: =SUMPRODUCT(Supuestos!$D$23:$D$35*((B16-Supuestos!$I$23:$I$35)>=Supuestos!$C$15)*((B16-Supuestos!$I$23:$I$35)<=Supuestos!$C$16)*(MOD((B16-Supuestos!$I$23:$I$35)-Supuestos!$C$15,6)=0))/Supuestos!$C$17 -> 0 | F16: =F15+D16-E16 -> 600.34 | G16: =F16/Supuestos!$C$5 -> 2.5003748 | H16: =MAX(0,F15-Supuestos!$C$18) -> 0 | I16: =IF(F16>Supuestos!$C$18,I15+1,0) -> 0 | J16: =F15*Supuestos!$C$19/12 -> 1.4581518 | K16: =H16*Supuestos!$C$11/12 -> 0 | L16: =IF(I15>Supuestos!$C$12,H16*Supuestos!$C$13/12,0) -> 0 | M16: =D16*Supuestos!$C$14 -> 0.4804 | N16: =SUM(J16:M16) -> 1.9385518 | O16: =E16+N16 -> 1.9385518
A17: =EDATE(A16,1) -> 46661 | B17: =YEAR(A17)*12+MONTH(A17) -> 24334 | C17: =YEAR(A17) -> 2027 | D17: =SUMIF(Supuestos!$I$23:$I$35,B17,Supuestos!$D$23:$D$35) -> 0 | E17: =SUMPRODUCT(Supuestos!$D$23:$D$35*((B17-Supuestos!$I$23:$I$35)>=Supuestos!$C$15)*((B17-Supuestos!$I$23:$I$35)<=Supuestos!$C$16)*(MOD((B17-Supuestos!$I$23:$I$35)-Supuestos!$C$15,6)=0))/Supuestos!$C$17 -> 0 | F17: =F16+D17-E17 -> 600.34 | G17: =F17/Supuestos!$C$5 -> 2.5003748 | H17: =MAX(0,F16-Supuestos!$C$18) -> 0 | I17: =IF(F17>Supuestos!$C$18,I16+1,0) -> 0 | J17: =F16*Supuestos!$C$19/12 -> 1.7359832 | K17: =H17*Supuestos!$C$11/12 -> 0 | L17: =IF(I16>Supuestos!$C$12,H17*Supuestos!$C$13/12,0) -> 0 | M17: =D17*Supuestos!$C$14 -> 0 | N17: =SUM(J17:M17) -> 1.7359832 | O17: =E17+N17 -> 1.7359832
... A163: =EDATE(A162,1) -> 51105 | B163: =YEAR(A163)*12+MONTH(A163) -> 24480 | C163: =YEAR(A163) -> 2039 | D163: =SUMIF(Supuestos!$I$23:$I$35,B163,Supuestos!$D$23:$D$35) -> 0 | E163: =SUMPRODUCT(Supuestos!$D$23:$D$35*((B163-Supuestos!$I$23:$I$35)>=Supuestos!$C$15)*((B163-Supuestos!$I$23:$I$35)<=Supuestos!$C$16)*(MOD((B163-Supuestos!$I$23:$I$35)-Supuestos!$C$15,6)=0))/Supuestos!$C$17 -> 0 | F163: =F162+D163-E163 -> 3.375078e-14 | G163: =F163/Supuestos!$C$5 -> 1.4056968e-16 | H163: =MAX(0,F162-Supuestos!$C$18) -> 0 | I163: =IF(F163>Supuestos!$C$18,I162+1,0) -> 0 | J163: =F162*Supuestos!$C$19/12 -> 9.7596005e-17 | K163: =H163*Supuestos!$C$11/12 -> 0 | L163: =IF(I162>Supuestos!$C$12,H163*Supuestos!$C$13/12,0) -> 0 | M163: =D163*Supuestos!$C$14 -> 0 | N163: =SUM(J163:M163) -> 9.7596005e-17 | O163: =E163+N163 -> 9.7596005e-17

Sheet Anual
A1: Resumen anual: flujos con el FMI
A2: DEG mm y USD mm (convertidos con el tipo de cambio USD/DEG de Supuestos, constante).
B4: Millones de DEG | L4: Millones de USD
A5: Año | B5: Desembolsos | C5: Repagos de capital | D5: Cargo básico | E5: Sobrecargos | F5: Cargo por servicio | G5: Cargos totales | H5: Servicio total | I5: Flujo neto (desemb. − servicio) | J5: Saldo a fin de año | K5: Saldo (% cuota) | L5: Desembolsos (USD) | M5: Repagos (USD) | N5: Cargos (USD) | O5: Servicio total (USD) | P5: Flujo neto (USD) | Q5: Saldo fin de año (USD)
A6: 2026 | B6: =SUMIF(Mensual!$C$5:$C$163,VALUE(A6),Mensual!$D$5:$D$163) -> 312.1 | C6: =SUMIF(Mensual!$C$5:$C$163,VALUE(A6),Mensual!$E$5:$E$163) -> 0 | D6: =SUMIF(Mensual!$C$5:$C$163,VALUE(A6),Mensual!$J$5:$J$163) -> 0.90277833 | E6: =SUMIF(Mensual!$C$5:$C$163,VALUE(A6),Mensual!$K$5:$K$163)+SUMIF(Mensual!$C$5:$C$163,VALUE(A6),Mensual!$L$5:$L$163) -> 0 | F6: =SUMIF(Mensual!$C$5:$C$163,VALUE(A6),Mensual!$M$5:$M$163) -> 1.5605 | G6: =D6+E6+F6 -> 2.4632783 | H6: =C6+G6 -> 2.4632783 | I6: =B6-H6 -> 309.63672 | J6: =SUMIF(Mensual!$B$5:$B$163,VALUE(A6)*12+12,Mensual!$F$5:$F$163) -> 312.1 | K6: =J6/Supuestos!$C$5 -> 1.2998751 | L6: =B6*Supuestos!$C$7 -> 422.46464 | M6: =C6*Supuestos!$C$7 -> 0 | N6: =G6*Supuestos!$C$7 -> 3.3343415 | O6: =H6*Supuestos!$C$7 -> 3.3343415 | P6: =I6*Supuestos!$C$7 -> 419.1303 | Q6: =J6*Supuestos!$C$7 -> 422.46464
A7: 2027 | B7: =SUMIF(Mensual!$C$5:$C$163,VALUE(A7),Mensual!$D$5:$D$163) -> 384.32 | C7: =SUMIF(Mensual!$C$5:$C$163,VALUE(A7),Mensual!$E$5:$E$163) -> 0 | D7: =SUMIF(Mensual!$C$5:$C$163,VALUE(A7),Mensual!$J$5:$J$163) -> 15.830834 | E7: =SUMIF(Mensual!$C$5:$C$163,VALUE(A7),Mensual!$K$5:$K$163)+SUMIF(Mensual!$C$5:$C$163,VALUE(A7),Mensual!$L$5:$L$163) -> 0 | F7: =SUMIF(Mensual!$C$5:$C$163,VALUE(A7),Mensual!$M$5:$M$163) -> 1.9216 | G7: =D7+E7+F7 -> 17.752434 | H7: =C7+G7 -> 17.752434 | I7: =B7-H7 -> 366.56757 | J7: =SUMIF(Mensual!$B$5:$B$163,VALUE(A7)*12+12,Mensual!$F$5:$F$163) -> 696.42 | K7: =J7/Supuestos!$C$5 -> 2.9005414 | L7: =B7*Supuestos!$C$7 -> 520.22304 | M7: =C7*Supuestos!$C$7 -> 0 | N7: =G7*Supuestos!$C$7 -> 24.03004 | O7: =H7*Supuestos!$C$7 -> 24.03004 | P7: =I7*Supuestos!$C$7 -> 496.193 | Q7: =J7*Supuestos!$C$7 -> 942.68767
A8: 2028 | B8: =SUMIF(Mensual!$C$5:$C$163,VALUE(A8),Mensual!$D$5:$D$163) -> 384.32 | C8: =SUMIF(Mensual!$C$5:$C$163,VALUE(A8),Mensual!$E$5:$E$163) -> 0 | D8: =SUMIF(Mensual!$C$5:$C$163,VALUE(A8),Mensual!$J$5:$J$163) -> 29.166738 | E8: =SUMIF(Mensual!$C$5:$C$163,VALUE(A8),Mensual!$K$5:$K$163)+SUMIF(Mensual!$C$5:$C$163,VALUE(A8),Mensual!$L$5:$L$163) -> 2.5242 | F8: =SUMIF(Mensual!$C$5:$C$163,VALUE(A8),Mensual!$M$5:$M$163) -> 1.9216 | G8: =D8+E8+F8 -> 33.612538 | H8: =C8+G8 -> 33.612538 | I8: =B8-H8 -> 350.70746 | J8: =SUMIF(Mensual!$B$5:$B$163,VALUE(A8)*12+12,Mensual!$F$5:$F$163) -> 1080.74 | K8: =J8/Supuestos!$C$5 -> 4.5012078 | L8: =B8*Supuestos!$C$7 -> 520.22304 | M8: =C8*Supuestos!$C$7 -> 0 | N8: =G8*Supuestos!$C$7 -> 45.498586 | O8: =H8*Supuestos!$C$7 -> 45.498586 | P8: =I8*Supuestos!$C$7 -> 474.72445 | Q8: =J8*Supuestos!$C$7 -> 1462.9107
A9: 2029 | B9: =SUMIF(Mensual!$C$5:$C$163,VALUE(A9),Mensual!$D$5:$D$163) -> 288.26 | C9: =SUMIF(Mensual!$C$5:$C$163,VALUE(A9),Mensual!$E$5:$E$163) -> 0 | D9: =SUMIF(Mensual!$C$5:$C$163,VALUE(A9),Mensual!$J$5:$J$163) -> 42.502815 | E9: =SUMIF(Mensual!$C$5:$C$163,VALUE(A9),Mensual!$K$5:$K$163)+SUMIF(Mensual!$C$5:$C$163,VALUE(A9),Mensual!$L$5:$L$163) -> 10.0913 | F9: =SUMIF(Mensual!$C$5:$C$163,VALUE(A9),Mensual!$M$5:$M$163) -> 1.4413 | G9: =D9+E9+F9 -> 54.035415 | H9: =C9+G9 -> 54.035415 | I9: =B9-H9 -> 234.22458 | J9: =SUMIF(Mensual!$B$5:$B$163,VALUE(A9)*12+12,Mensual!$F$5:$F$163) -> 1369 | K9: =J9/Supuestos!$C$5 -> 5.7017909 | L9: =B9*Supuestos!$C$7 -> 390.19435 | M9: =C9*Supuestos!$C$7 -> 0 | N9: =G9*Supuestos!$C$7 -> 73.143391 | O9: =H9*Supuestos!$C$7 -> 73.143391 | P9: =I9*Supuestos!$C$7 -> 317.05096 | Q9: =J9*Supuestos!$C$7 -> 1853.1051
A10: 2030 | B10: =SUMIF(Mensual!$C$5:$C$163,VALUE(A10),Mensual!$D$5:$D$163) -> 0 | C10: =SUMIF(Mensual!$C$5:$C$163,VALUE(A10),Mensual!$E$5:$E$163) -> 0 | D10: =SUMIF(Mensual!$C$5:$C$163,VALUE(A10),Mensual!$J$5:$J$163) -> 47.5043 | E10: =SUMIF(Mensual!$C$5:$C$163,VALUE(A10),Mensual!$K$5:$K$163)+SUMIF(Mensual!$C$5:$C$163,VALUE(A10),Mensual!$L$5:$L$163) -> 12.974 | F10: =SUMIF(Mensual!$C$5:$C$163,VALUE(A10),Mensual!$M$5:$M$163) -> 0 | G10: =D10+E10+F10 -> 60.4783 | H10: =C10+G10 -> 60.4783 | I10: =B10-H10 -> -60.4783 | J10: =SUMIF(Mensual!$B$5:$B$163,VALUE(A10)*12+12,Mensual!$F$5:$F$163) -> 1369 | K10: =J10/Supuestos!$C$5 -> 5.7017909 | L10: =B10*Supuestos!$C$7 -> 0 | M10: =C10*Supuestos!$C$7 -> 0 | N10: =G10*Supuestos!$C$7 -> 81.864605 | O10: =H10*Supuestos!$C$7 -> 81.864605 | P10: =I10*Supuestos!$C$7 -> -81.864605 | Q10: =J10*Supuestos!$C$7 -> 1853.1051
A11: 2031 | B11: =SUMIF(Mensual!$C$5:$C$163,VALUE(A11),Mensual!$D$5:$D$163) -> 0 | C11: =SUMIF(Mensual!$C$5:$C$163,VALUE(A11),Mensual!$E$5:$E$163) -> 68.03 | D11: =SUMIF(Mensual!$C$5:$C$163,VALUE(A11),Mensual!$J$5:$J$163) -> 46.833135 | E11: =SUMIF(Mensual!$C$5:$C$163,VALUE(A11),Mensual!$K$5:$K$163)+SUMIF(Mensual!$C$5:$C$163,VALUE(A11),Mensual!$L$5:$L$163) -> 12.587161 | F11: =SUMIF(Mensual!$C$5:$C$163,VALUE(A11),Mensual!$M$5:$M$163) -> 0 | G11: =D11+E11+F11 -> 59.420296 | H11: =C11+G11 -> 127.4503 | I11: =B11-H11 -> -127.4503 | J11: =SUMIF(Mensual!$B$5:$B$163,VALUE(A11)*12+12,Mensual!$F$5:$F$163) -> 1300.97 | K11: =J11/Supuestos!$C$5 -> 5.4184506 | L11: =B11*Supuestos!$C$7 -> 0 | M11: =C11*Supuestos!$C$7 -> 92.086733 | N11: =G11*Supuestos!$C$7 -> 80.432469 | O11: =H11*Supuestos!$C$7 -> 172.5192 | P11: =I11*Supuestos!$C$7 -> -172.5192 | Q11: =J11*Supuestos!$C$7 -> 1761.0183
A12: 2032 | B12: =SUMIF(Mensual!$C$5:$C$163,VALUE(A12),Mensual!$D$5:$D$163) -> 0 | C12: =SUMIF(Mensual!$C$5:$C$163,VALUE(A12),Mensual!$E$5:$E$163) -> 132.08333 | D12: =SUMIF(Mensual!$C$5:$C$163,VALUE(A12),Mensual!$J$5:$J$163) -> 43.639 | E12: =SUMIF(Mensual!$C$5:$C$163,VALUE(A12),Mensual!$K$5:$K$163)+SUMIF(Mensual!$C$5:$C$163,VALUE(A12),Mensual!$L$5:$L$163) -> 12.644744 | F12: =SUMIF(Mensual!$C$5:$C$163,VALUE(A12),Mensual!$M$5:$M$163) -> 0 | G12: =D12+E12+F12 -> 56.283744 | H12: =C12+G12 -> 188.36708 | I12: =B12-H12 -> -188.36708 | J12: =SUMIF(Mensual!$B$5:$B$163,VALUE(A12)*12+12,Mensual!$F$5:$F$163) -> 1168.8867 | K12: =J12/Supuestos!$C$5 -> 4.8683326 | L12: =B12*Supuestos!$C$7 -> 0 | M12: =C12*Supuestos!$C$7 -> 178.79057 | N12: =G12*Supuestos!$C$7 -> 76.186772 | O12: =H12*Supuestos!$C$7 -> 254.97734 | P12: =I12*Supuestos!$C$7 -> -254.97734 | Q12: =J12*Supuestos!$C$7 -> 1582.2278
A13: 2033 | B13: =SUMIF(Mensual!$C$5:$C$163,VALUE(A13),Mensual!$D$5:$D$163) -> 0 | C13: =SUMIF(Mensual!$C$5:$C$163,VALUE(A13),Mensual!$E$5:$E$163) -> 196.13667 | D13: =SUMIF(Mensual!$C$5:$C$163,VALUE(A13),Mensual!$J$5:$J$163) -> 38.222214 | E13: =SUMIF(Mensual!$C$5:$C$163,VALUE(A13),Mensual!$K$5:$K$163)+SUMIF(Mensual!$C$5:$C$163,VALUE(A13),Mensual!$L$5:$L$163) -> 10.48313 | F13: =SUMIF(Mensual!$C$5:$C$163,VALUE(A13),Mensual!$M$5:$M$163) -> 0 | G13: =D13+E13+F13 -> 48.705344 | H13: =C13+G13 -> 244.84201 | I13: =B13-H13 -> -244.84201 | J13: =SUMIF(Mensual!$B$5:$B$163,VALUE(A13)*12+12,Mensual!$F$5:$F$163) -> 972.75 | K13: =J13/Supuestos!$C$5 -> 4.0514369 | L13: =B13*Supuestos!$C$7 -> 0 | M13: =C13*Supuestos!$C$7 -> 265.49441 | N13: =G13*Supuestos!$C$7 -> 65.928502 | O13: =H13*Supuestos!$C$7 -> 331.42291 | P13: =I13*Supuestos!$C$7 -> -331.42291 | Q13: =J13*Supuestos!$C$7 -> 1316.7333
A14: 2034 | B14: =SUMIF(Mensual!$C$5:$C$163,VALUE(A14),Mensual!$D$5:$D$163) -> 0 | C14: =SUMIF(Mensual!$C$5:$C$163,VALUE(A14),Mensual!$E$5:$E$163) -> 228.16667 | D14: =SUMIF(Mensual!$C$5:$C$163,VALUE(A14),Mensual!$J$5:$J$163) -> 30.791093 | E14: =SUMIF(Mensual!$C$5:$C$163,VALUE(A14),Mensual!$K$5:$K$163)+SUMIF(Mensual!$C$5:$C$163,VALUE(A14),Mensual!$L$5:$L$163) -> 4.5939132 | F14: =SUMIF(Mensual!$C$5:$C$163,VALUE(A14),Mensual!$M$5:$M$163) -> 0 | G14: =D14+E14+F14 -> 35.385006 | H14: =C14+G14 -> 263.55167 | I14: =B14-H14 -> -263.55167 | J14: =SUMIF(Mensual!$B$5:$B$163,VALUE(A14)*12+12,Mensual!$F$5:$F$163) -> 744.58333 | K14: =J14/Supuestos!$C$5 -> 3.1011384 | L14: =B14*Supuestos!$C$7 -> 0 | M14: =C14*Supuestos!$C$7 -> 308.85084 | N14: =G14*Supuestos!$C$7 -> 47.897834 | O14: =H14*Supuestos!$C$7 -> 356.74868 | P14: =I14*Supuestos!$C$7 -> -356.74868 | Q14: =J14*Supuestos!$C$7 -> 1007.8825
A15: 2035 | B15: =SUMIF(Mensual!$C$5:$C$163,VALUE(A15),Mensual!$D$5:$D$163) -> 0 | C15: =SUMIF(Mensual!$C$5:$C$163,VALUE(A15),Mensual!$E$5:$E$163) -> 228.16667 | D15: =SUMIF(Mensual!$C$5:$C$163,VALUE(A15),Mensual!$J$5:$J$163) -> 22.87371 | E15: =SUMIF(Mensual!$C$5:$C$163,VALUE(A15),Mensual!$K$5:$K$163)+SUMIF(Mensual!$C$5:$C$163,VALUE(A15),Mensual!$L$5:$L$163) -> 0.16694792 | F15: =SUMIF(Mensual!$C$5:$C$163,VALUE(A15),Mensual!$M$5:$M$163) -> 0 | G15: =D15+E15+F15 -> 23.040658 | H15: =C15+G15 -> 251.20732 | I15: =B15-H15 -> -251.20732 | J15: =SUMIF(Mensual!$B$5:$B$163,VALUE(A15)*12+12,Mensual!$F$5:$F$163) -> 516.41667 | K15: =J15/Supuestos!$C$5 -> 2.1508399 | L15: =B15*Supuestos!$C$7 -> 0 | M15: =C15*Supuestos!$C$7 -> 308.85084 | N15: =G15*Supuestos!$C$7 -> 31.188283 | O15: =H15*Supuestos!$C$7 -> 340.03913 | P15: =I15*Supuestos!$C$7 -> -340.03913 | Q15: =J15*Supuestos!$C$7 -> 699.03166
A16: 2036 | B16: =SUMIF(Mensual!$C$5:$C$163,VALUE(A16),Mensual!$D$5:$D$163) -> 0 | C16: =SUMIF(Mensual!$C$5:$C$163,VALUE(A16),Mensual!$E$5:$E$163) -> 228.16667 | D16: =SUMIF(Mensual!$C$5:$C$163,VALUE(A16),Mensual!$J$5:$J$163) -> 14.956327 | E16: =SUMIF(Mensual!$C$5:$C$163,VALUE(A16),Mensual!$K$5:$K$163)+SUMIF(Mensual!$C$5:$C$163,VALUE(A16),Mensual!$L$5:$L$163) -> 0 | F16: =SUMIF(Mensual!$C$5:$C$163,VALUE(A16),Mensual!$M$5:$M$163) -> 0 | G16: =D16+E16+F16 -> 14.956327 | H16: =C16+G16 -> 243.12299 | I16: =B16-H16 -> -243.12299 | J16: =SUMIF(Mensual!$B$5:$B$163,VALUE(A16)*12+12,Mensual!$F$5:$F$163) -> 288.25 | K16: =J16/Supuestos!$C$5 -> 1.2005414 | L16: =B16*Supuestos!$C$7 -> 0 | M16: =C16*Supuestos!$C$7 -> 308.85084 | N16: =G16*Supuestos!$C$7 -> 20.245175 | O16: =H16*Supuestos!$C$7 -> 329.09602 | P16: =I16*Supuestos!$C$7 -> -329.09602 | Q16: =J16*Supuestos!$C$7 -> 390.18081
A17: 2037 | B17: =SUMIF(Mensual!$C$5:$C$163,VALUE(A17),Mensual!$D$5:$D$163) -> 0 | C17: =SUMIF(Mensual!$C$5:$C$163,VALUE(A17),Mensual!$E$5:$E$163) -> 160.13667 | D17: =SUMIF(Mensual!$C$5:$C$163,VALUE(A17),Mensual!$J$5:$J$163) -> 7.7101087 | E17: =SUMIF(Mensual!$C$5:$C$163,VALUE(A17),Mensual!$K$5:$K$163)+SUMIF(Mensual!$C$5:$C$163,VALUE(A17),Mensual!$L$5:$L$163) -> 0 | F17: =SUMIF(Mensual!$C$5:$C$163,VALUE(A17),Mensual!$M$5:$M$163) -> 0 | G17: =D17+E17+F17 -> 7.7101087 | H17: =C17+G17 -> 167.84678 | I17: =B17-H17 -> -167.84678 | J17: =SUMIF(Mensual!$B$5:$B$163,VALUE(A17)*12+12,Mensual!$F$5:$F$163) -> 128.11333 | K17: =J17/Supuestos!$C$5 -> 0.53358323 | L17: =B17*Supuestos!$C$7 -> 0 | M17: =C17*Supuestos!$C$7 -> 216.76411 | N17: =G17*Supuestos!$C$7 -> 10.436553 | O17: =H17*Supuestos!$C$7 -> 227.20066 | P17: =I17*Supuestos!$C$7 -> -227.20066 | Q17: =J17*Supuestos!$C$7 -> 173.4167
... A19: 2039 | B19: =SUMIF(Mensual!$C$5:$C$163,VALUE(A19),Mensual!$D$5:$D$163) -> 0 | C19: =SUMIF(Mensual!$C$5:$C$163,VALUE(A19),Mensual!$E$5:$E$163) -> 32.03 | D19: =SUMIF(Mensual!$C$5:$C$163,VALUE(A19),Mensual!$J$5:$J$163) -> 0.48626267 | E19: =SUMIF(Mensual!$C$5:$C$163,VALUE(A19),Mensual!$K$5:$K$163)+SUMIF(Mensual!$C$5:$C$163,VALUE(A19),Mensual!$L$5:$L$163) -> 0 | F19: =SUMIF(Mensual!$C$5:$C$163,VALUE(A19),Mensual!$M$5:$M$163) -> 0 | G19: =D19+E19+F19 -> 0.48626267 | H19: =C19+G19 -> 32.516263 | I19: =B19-H19 -> -32.516263 | J19: =SUMIF(Mensual!$B$5:$B$163,VALUE(A19)*12+12,Mensual!$F$5:$F$163) -> 3.375078e-14 | K19: =J19/Supuestos!$C$5 -> 1.4056968e-16 | L19: =B19*Supuestos!$C$7 -> 0 | M19: =C19*Supuestos!$C$7 -> 43.356432 | N19: =G19*Supuestos!$C$7 -> 0.65821462 | O19: =H19*Supuestos!$C$7 -> 44.014646 | P19: =I19*Supuestos!$C$7 -> -44.014646 | Q19: =J19*Supuestos!$C$7 -> 4.5685713e-14
A20: Total | B20: =SUM(B6:B19) -> 1369 | C20: =SUM(C6:C19) -> 1369 | D20: =SUM(D6:D19) -> 344.40618 | E20: =SUM(E6:E19) -> 66.065397 | F20: =SUM(F6:F19) -> 6.845 | G20: =SUM(G6:G19) -> 417.31657 | H20: =SUM(H6:H19) -> 1786.3166 | I20: =SUM(I6:I19) -> -417.31657 | L20: =SUM(L6:L19) -> 1853.1051 | M20: =SUM(M6:M19) -> 1853.1051 | N20: =SUM(N6:N19) -> 564.88784 | O20: =SUM(O6:O19) -> 2417.9929 | P20: =SUM(P6:P19) -> -564.88784
A22: Indicadores
A23: Saldo máximo (DEG mm) | C23: =MAX(Mensual!$F$5:$F$163) -> 1369
A24: Saldo máximo (% cuota) | C24: =MAX(Mensual!$G$5:$G$163) -> 5.7017909
A25: Mes del saldo máximo | C25: =INDEX(Mensual!$A$5:$A$163,MATCH(MAX(Mensual!$F$5:$F$163),Mensual!$F$5:$F$163,0)) -> 47362
A26: Primer repago de capital | C26: =MIN(Supuestos!$J$23:$J$35) -> 47939
A27: Último repago de capital | C27: =MAX(Supuestos!$K$23:$K$35) -> 51014
A28: Año de mayor servicio total (USD mm) | C28: =INDEX(A6:A19,MATCH(MAX(O6:O19),O6:O19,0)) -> 2034
A29: Servicio total en ese año (USD mm) | C29: =MAX(O6:O19) -> 356.74868
A30: Costo financiero total / monto girado | C30: =G20/B20 -> 0.30483314
A31: Meses con sobrecargo por tiempo | C31: =COUNTIF(Mensual!$L$5:$L$163,">0") -> 33

Sheet Notas_Fuentes
A1: Notas metodológicas y fuentes
A3: • Dato: el acuerdo SAF de 36 meses, por DEG 1.369 mm (570% de la cuota), fue aprobado el 2-oct-2026. El primer giro fue de DEG 156,1 mm (USD 211,3 mm), recibido por el BCB.
A4: • Supuesto: el calendario de revisiones posteriores. Las fuentes consultadas no publican el cuadro de fases del staff report. Se puede editar en Supuestos (fechas y montos).
A5: • Repago: cada giro se devuelve en 12 cuotas semestrales iguales, desde los 4,5 años hasta los 10 años posteriores al giro.
A6: • Cargo básico: tasa de interés del DEG + 60 pb. La tasa del DEG es variable (se fija semanalmente); acá se supone constante en 2,87%, el valor implícito en el 3,47% informado.
A7: • Sobrecargos: 200 pb sobre el crédito que excede el 300% de la cuota. Se suman 75 pb si ese exceso se mantiene más de 51 meses (SAF).
A8: • Cargo por servicio: 50 pb sobre cada giro. No se incluye la comisión de compromiso porque se reembolsa a medida que se gira; sólo sería un costo neto si no se completa el acceso.
A9: • Simplificaciones: los cargos se devengan mensualmente sobre el saldo del mes anterior (el FMI liquida trimestralmente y por saldo diario), y la conversión a USD usa un tipo USD/DEG constante.
A10: • Esta hoja reemplaza la aproximación anual del FMI usada en DSA_Bolivia.xlsx (USD 0,43 / 0,62 / 0,62 / 0,23 mm M en 2026-29, con repagos lineales de 1/6 por año).
A12: Fuentes
A13: FMI, comunicado de aprobación del SAF (2-oct-2026) | B13: https://www.imf.org/es/news/articles/2026/10/02/pr26317-bolivia-imf-approves-36-month-eff-arrangement
A14: BCB confirma el primer desembolso: USD 211,3 mm = DEG 156,1 mm | B14: https://eldeber.com.bo/economia/banco-central-bolivia-confirma-primer-desembolso-us-211-3-millones-fmi_1791317879
A15: Condiciones: tasa 3,47%, repago desde 4 años y 6 meses hasta 10 años | B15: https://www.economy.com.bo/articulo/economia/fmi-aprueba-financiamiento-us-1900-millones-bolivia-desembolso-inmediato-us-214-millones/20261002185448024301.html
A16: Ministro: segundo desembolso nov-dic 2026, luego trimestrales | B16: https://www.reduno.com.bo/economia/bolivia-recibira-us-214-millones-del-fmi-para-fortalecer-reservas-y-preve-nuevos-desembolsos-202610674812
A17: FMI, reforma de cargos y sobrecargos (oct-2024) | B17: https://www.imf.org/en/News/Articles/2024/10/21/pr-24385-imf-concludes-the-review-of-charges-and-surcharge-policy-and-approves-reforms
A18: FMI, preguntas frecuentes sobre cargos y sobrecargos | B18: https://www.imf.org/en/about/faq/charges-and-surcharge-policy
