Workbook

Sheet Portada
A1: Bolivia: análisis de sostenibilidad de deuda con bloque externo integrado
A2: Modelo anual 2025-2035. Deuda pública del SPNF + balanza de pagos + reservas + tipo de cambio endógeno. Elaborado el 14-oct-2026 con información pública disponible a esa fecha.
A4: Cómo usarlo
A5: Cambie C6 para ver cualquier escenario en las hojas Externo, Fiscal_Deuda e Indicadores. Insumos en azul (hoja Supuestos). Las hojas Escenarios y Estocastico son salidas del motor en Python (modelo.py), con las mismas ecuaciones.
A6: Escenario activo (1-8) ► | C6: 1 | D6: =INDEX(Supuestos!$B$81:$B$88,C6) -> Base
A8: Resultados clave (escenario activo, fórmulas vivas)
A9: Indicador | C9: 2026 | D9: 2027 | E9: 2029 | F9: 2031 | G9: 2035
A10: Deuda pública / PIB | C10: =Indicadores!D6 -> 1.0019902 | D10: =Indicadores!E6 -> 0.99288556 | E10: =Indicadores!G6 -> 0.9403403 | F10: =Indicadores!I6 -> 0.89207427 | G10: =Indicadores!M6 -> 0.84057989
A11: Deuda neta de BCB / PIB | C11: =Indicadores!D7 -> 0.69994763 | D11: =Indicadores!E7 -> 0.71073658 | E11: =Indicadores!G7 -> 0.69571457 | F11: =Indicadores!I7 -> 0.67255971 | G11: =Indicadores!M7 -> 0.67903907
A12: NBF / PIB | C12: =Indicadores!D8 -> 0.21292044 | D12: =Indicadores!E8 -> 0.20060846 | E12: =Indicadores!G8 -> 0.16097801 | F12: =Indicadores!I8 -> 0.15400353 | G12: =Indicadores!M8 -> 0.14293998
A13: Balance global / PIB | C13: =Indicadores!D9 -> -0.092015157 | D13: =Indicadores!E9 -> -0.067000528 | E13: =Indicadores!G9 -> -0.031995997 | F13: =Indicadores!I9 -> -0.03004509 | G13: =Indicadores!M9 -> -0.030023966
A14: Deuda externa total / PIB | C14: =Indicadores!D14 -> 0.39056852 | D14: =Indicadores!E14 -> 0.48380488 | E14: =Indicadores!G14 -> 0.49746474 | F14: =Indicadores!I14 -> 0.46156417 | G14: =Indicadores!M14 -> 0.42624984
A15: Servicio deuda ext. / export. | C15: =Indicadores!D17 -> 0.12192647 | D15: =Indicadores!E17 -> 0.13860018 | E15: =Indicadores!G17 -> 0.15110217 | F15: =Indicadores!I17 -> 0.15770893 | G15: =Indicadores!M17 -> 0.16782269
A16: Cuenta corriente / PIB | C16: =Indicadores!D18 -> 0.013354343 | D16: =Indicadores!E18 -> 0.011291266 | E16: =Indicadores!G18 -> -0.015467896 | F16: =Indicadores!I18 -> -0.029568877 | G16: =Indicadores!M18 -> -0.0057590364
A17: Reservas brutas (USD mm M) | C17: =Indicadores!D19 -> 5.1938 | D17: =Indicadores!E19 -> 6.5742787 | E17: =Indicadores!G19 -> 8.0313368 | F17: =Indicadores!I19 -> 7.1117231 | G17: =Indicadores!M19 -> 4.2532437
A18: Reservas (meses de import.) | C18: =Indicadores!D20 -> 5.3728966 | D18: =Indicadores!E20 -> 6.9045593 | E18: =Indicadores!G20 -> 7.8169205 | F18: =Indicadores!I20 -> 6.3247209 | G18: =Indicadores!M20 -> 3.7512868
A19: Tipo de cambio (Bs/USD) | C19: =Indicadores!D25 -> 11.8 | D19: =Indicadores!E25 -> 12.755073 | E19: =Indicadores!G25 -> 13.662347 | F19: =Indicadores!I25 -> 14.255967 | G19: =Indicadores!M25 -> 19.681527
A20: Depreciación de ajuste endógena | C20: =Indicadores!D24 -> 0 | D20: =Indicadores!E24 -> 0 | E20: =Indicadores!G24 -> 0 | F20: =Indicadores!I24 -> 0 | G20: =Indicadores!M24 -> 0.074858337
A22: Lectura de colores
A23: Azul | C23: insumo editable
A24: Negro | C24: fórmula
A25: Verde | C25: vínculo a otra hoja
A26: Fondo amarillo | C26: supuesto clave / selector
A27: Fondo gris | C27: 2025 dato, 2026 estimación

Sheet Supuestos
A1: Supuestos del modelo
A2: Celdas en azul = insumos editables. Gris = 2025 (dato) y 2026 (estimación). Amarillo = supuestos clave. Los escenarios aplican choques sobre estas sendas a partir de 2027.
C3: dato | D3: estim.
A4: Concepto | B4: Unidad | C4: 2025 | D4: 2026 | E4: 2027 | F4: 2028 | G4: 2029 | H4: 2030 | I4: 2031 | J4: 2032 | K4: 2033 | L4: 2034 | M4: 2035 | N4: Nota / fuente
A5: Macro
A6: Crecimiento real (base) | B6: % | C6: -0.016 | D6: -0.03 | E6: -0.015 | F6: 0.005 | G6: 0.02 | H6: 0.025 | I6: 0.028 | J6: 0.028 | K6: 0.028 | L6: 0.028 | M6: 0.028 | N6: 2025: INE. 2026-28: FMI (WEO oct-2026 / staff report EFF). 2029+: supuesto propio
A7: Deflactor del PIB (base) | B7: % | C7: 0.2 | D7: 0.18 | E7: 0.14 | F7: 0.09 | G7: 0.06 | H7: 0.05 | I7: 0.04 | J7: 0.04 | K7: 0.04 | L7: 0.04 | M7: 0.04 | N7: Supuesto propio; FMI: IPC prom. 12,7% (2026), 15,8% (2027)
A8: Inflación EE.UU. | B8: % | C8: 0.025 | D8: 0.025 | E8: 0.023 | F8: 0.023 | G8: 0.023 | H8: 0.023 | I8: 0.023 | J8: 0.023 | K8: 0.023 | L8: 0.023 | M8: 0.023 | N8: Supuesto
A9: Var. tipo de cambio real (base; + = depreciación) | B9: % | C9: 0 | D9: 0 | E9: -0.03 | F9: -0.02 | G9: -0.01 | H9: 0 | I9: 0 | J9: 0 | K9: 0 | L9: 0 | M9: 0 | N9: Corrección parcial del overshooting post-flotación (jun-2026)
A10: Tipo de cambio fin de año (dato/estim.) | B10: Bs/USD | C10: 6.96 | D10: 11.8 | E10: 11.8 | F10: 11.8 | G10: 11.8 | H10: 11.8 | I10: 11.8 | J10: 11.8 | K10: 11.8 | L10: 11.8 | M10: 11.8 | N10: 6,96 (2025, oficial); ~11,7-11,8 oct-2026 (BCB, flotación desde RM 245/2026)
A11: Precios externos (índice 2025=100)
A12: Precios metales preciosos (plata/oro, export.) | B12: índice | C12: 100 | D12: 175 | E12: 161 | F12: 153 | G12: 153 | H12: 153 | I12: 153 | J12: 153 | K12: 153 | L12: 153 | M12: 153 | N12: Calibrado: export. minerales +91% en valor con -12% volumen (IBCE, 1S-2026)
A13: Precios metales base (zinc, estaño, plomo) | B13: índice | C13: 100 | D13: 115 | E13: 115 | F13: 115 | G13: 115 | H13: 115 | I13: 115 | J13: 115 | K13: 115 | L13: 115 | M13: 115 | N13: Supuesto
A14: Precio petróleo (Brent) | B14: índice | C14: 100 | D14: 112 | E14: 100 | F14: 97 | G14: 97 | H14: 97 | I14: 97 | J14: 97 | K14: 97 | L14: 97 | M14: 97 | N14: Supuesto; gas a Brasil indexado con 1 año de rezago
A15: Precio del oro (valuación reservas) | B15: índice | C15: 100 | D15: 140 | E15: 129 | F15: 122 | G15: 122 | H15: 122 | I15: 122 | J15: 122 | K15: 122 | L15: 122 | M15: 122 | N15: Supuesto
A16: Var. precios agro (soya y otros) | B16: % | C16: 0 | D16: 0 | E16: 0 | F16: 0 | G16: 0 | H16: 0 | I16: 0 | J16: 0 | K16: 0 | L16: 0 | M16: 0 | N16: Supuesto: plano
A17: Volúmenes (var. anual)
A18: Volumen metales preciosos | B18: % | C18: 0 | D18: 0 | E18: 0.02 | F18: 0.02 | G18: 0.02 | H18: 0.02 | I18: 0.02 | J18: 0.02 | K18: 0.02 | L18: 0.02 | M18: 0.02 | N18: Supuesto
A19: Volumen metales base | B19: % | C19: 0 | D19: 0 | E19: 0.01 | F19: 0.01 | G19: 0.01 | H19: 0.01 | I19: 0.01 | J19: 0.01 | K19: 0.01 | L19: 0.01 | M19: 0.01 | N19: Supuesto
A20: Volumen exportado de gas | B20: % | C20: 0 | D20: 0 | E20: -0.12 | F20: -0.12 | G20: -0.12 | H20: -0.12 | I20: -0.06 | J20: -0.06 | K20: -0.06 | L20: -0.06 | M20: -0.06 | N20: Declinación de campos maduros; export. de gas -33% en 2025 (INE)
A21: Volumen agro | B21: % | C21: 0 | D21: 0 | E21: 0.03 | F21: 0.03 | G21: 0.03 | H21: 0.03 | I21: 0.03 | J21: 0.03 | K21: 0.03 | L21: 0.03 | M21: 0.03 | N21: Supuesto
A22: Volumen importado de combustibles | B22: % | C22: 0 | D22: 0 | E22: -0.04 | F22: 0.02 | G22: 0.02 | H22: 0.02 | I22: 0.02 | J22: 0.02 | K22: 0.02 | L22: 0.02 | M22: 0.02 | N22: Fin de subsidios reduce contrabando; luego crece con actividad
A23: Balanza de pagos: valores iniciales (USD miles de millones)
A24: Export. metales preciosos | B24: USD mm M | C24: 2.8 | D24: 6.6 | N24: 2025: BCB/INE aprox.; 2026: anualización ene-ago (INE: USD 8.987 M acumulado)
A25: Export. metales base | B25: USD mm M | C25: 2.2 | D25: 2.7 | N25: Ídem
A26: Export. hidrocarburos | B26: USD mm M | C26: 1.6 | D26: 1 | N26: 2025: gas USD 1.077 M + otros (INE); 1S-2026: USD 498 M
A27: Export. agro (soya y derivados, otros) | B27: USD mm M | C27: 1.9 | D27: 2.2 | N27: Ídem
A28: Export. resto (manufacturas no tradicionales) | B28: USD mm M | C28: 1 | D28: 1.1 | N28: Ídem
A29: Import. combustibles | B29: USD mm M | C29: 2.8 | D29: 2.8 | N29: Estimación propia
A30: Import. resto (FOB) | B30: USD mm M | C30: 6.37 | D30: 8.8 | N30: 2025 calibrado a balanza de bienes +0,33 (BCB)
A31: Servicios (neto) | B31: USD mm M | C31: -1.5 | D31: -1.4 | N31: BCB, BoP 2025; 2026 estim.
A32: Ingreso secundario (remesas, neto) | B32: USD mm M | C32: 1.05 | D32: 1.35 | N32: BCB; 2026 estim.
A33: Cuenta financiera (USD miles de millones, flujos)
A34: IED neta | B34: USD mm M | C34: 0.1 | D34: 0.3 | E34: 0.5 | F34: 0.7 | G34: 0.9 | H34: 1 | I34: 1 | J34: 1 | K34: 1 | L34: 1 | M34: 1 | N34: Supuesto: recuperación gradual con nueva ley de hidrocarburos/litio
A35: Desembolsos deuda externa pública (excl. FMI) | B35: USD mm M | C35: 1.3 | D35: 1.6 | E35: 2 | F35: 1.7 | G35: 1.5 | H35: 1.3 | I35: 1.3 | J35: 1.3 | K35: 1.3 | L35: 1.3 | M35: 1.3 | N35: >USD 1.000 M BM/BID nov-dic 2026; ~USD 5.000 M esperados de otros acreedores durante el programa
A36: Amortizaciones deuda externa pública | B36: USD mm M | C36: 1 | D36: 0.95 | E36: 1.05 | F36: 1.1 | G36: 1.05 | H36: 1.3 | I36: 1.1 | J36: 1.1 | K36: 1.15 | L36: 1.15 | M36: 1.2 | N36: Estimación propia de cronograma (multilateral + bilateral + bonos 2028/2030 en manos externas)
A37: Reperfilamiento: alivio (bilateral + bonos) | B37: USD mm M | C37: 0 | D37: 0 | E37: 0.3 | F37: 0.32 | G37: 0.2 | H37: 0.48 | I37: 0.2 | J37: 0 | K37: 0 | L37: 0 | M37: 0 | N37: Sólo activo en escenario de reperfilamiento: diferimiento 5 años
A38: Reperfilamiento: repago diferido | B38: USD mm M | C38: 0 | D38: 0 | E38: 0 | F38: 0 | G38: 0 | H38: 0 | I38: 0 | J38: 0.3 | K38: 0.32 | L38: 0.2 | M38: 0.48 | N38: Ídem
A39: Desembolsos FMI (SAF) | B39: USD mm M | C39: 0 | D39: 0.43 | E39: 0.62 | F39: 0.62 | G39: 0.23 | H39: 0 | I39: 0 | J39: 0 | K39: 0 | L39: 0 | M39: 0 | N39: SAF 36 meses, DEG 1.369 M (~USD 1.900 M); USD 214 M en oct-2026
A40: Otros flujos privados netos (incl. errores y omisiones) | B40: USD mm M | C40: -1.6 | D40: -1.5 | E40: -0.9 | F40: -0.6 | G40: -0.4 | H40: -0.3 | I40: -0.3 | J40: -0.3 | K40: -0.3 | L40: -0.3 | M40: -0.3 | N40: 2026 calibrado a reservas ~5,2 mm M fin de año
A41: Fiscal y deuda
A42: Balance primario no-commodity (SPNF) | B42: % PIB | C42: -0.0715 | D42: -0.0643 | E42: -0.0343 | F42: -0.0063 | G42: 0.0077 | H42: 0.007 | I42: 0.0043 | J42: 0.0041 | K42: 0.0034 | L42: 0.0019 | M42: 0.0015 | N42: Calibrado para replicar el déficit global del programa: 9,2% (2026), 6,7% (2027), 4,5% (2028), 3,2% (2029), 3,0% después
A43: Subsidio a combustibles / import. combustibles | B43: % | C43: 0.5 | D43: 0.15 | E43: 0.05 | F43: 0 | G43: 0 | H43: 0 | I43: 0 | J43: 0 | K43: 0 | L43: 0 | M43: 0 | N43: Eliminación dic-2025; remanente se elimina en 2027 (mecanismo automático)
A44: Tasa efectiva deuda interna | B44: % | C44: 0.05 | D44: 0.05 | E44: 0.065 | F44: 0.075 | G44: 0.075 | H44: 0.07 | I44: 0.065 | J44: 0.065 | K44: 0.065 | L44: 0.065 | M44: 0.065 | N44: Supuesto: sube a medida que se corta financiamiento BCB
A45: Tasa efectiva deuda externa pública | B45: % | C45: 0.045 | D45: 0.05 | E45: 0.052 | F45: 0.052 | G45: 0.052 | H45: 0.052 | I45: 0.052 | J45: 0.052 | K45: 0.052 | L45: 0.052 | M45: 0.052 | N45: Supuesto (multilateral SOFR+, bonos 4,5%/7,5%)
A46: Deuda interna en moneda local en manos del BCB | B46: % | C46: 0.55 | D46: 0.55 | E46: 0.53 | F46: 0.51 | G46: 0.49 | H46: 0.47 | I46: 0.45 | J46: 0.43 | K46: 0.41 | L46: 0.39 | M46: 0.37 | N46: BCB ~54,6% de la deuda interna (Jubileo/ANF); cae 2 pp/año
A47: Deuda interna en USD o indexada (MVDOL) | B47: USD mm M | C47: 2 | D47: 2 | E47: 2 | F47: 2 | G47: 2 | H47: 2 | I47: 2 | J47: 2 | K47: 2 | L47: 2 | M47: 2 | N47: Supuesto; incluye bonos canjeados a MVDOL (mar-2026)
A49: Parámetros (elasticidades, umbrales y anclas 2025)
A50: Renta fiscal hidrocarburos / valor exportado | C50: 0.45 | D50: IDH 32% + regalías 18% sobre valor en boca de pozo, neto
A51: Renta fiscal minera / valor exportado | C51: 0.06 | D51: Regalías + IUE; baja por peso de cooperativas
A52: Elasticidad export. no tradicionales al TCR | C52: 0.5 | D52: Supuesto
A53: Elasticidad import. al TCR | C53: 0.8 | D53: Supuesto
A54: Elasticidad ingreso de importaciones | C54: 1.2 | D54: Supuesto
A55: Elasticidad de corto plazo para cerrar brecha externa | C55: 0.5 | D55: Devaluación requerida = brecha / (elasticidad x import.)
A56: Costo en crecimiento por punto de devaluación de ajuste | C56: 0.15 | D56: Devaluación contractiva (efecto hoja de balance + compresión de import.)
A57: Pass-through de la devaluación al deflactor | C57: 0.5 | D57: Supuesto
A58: Piso duro de reservas | C58: 2.5 | D58: Meses de importaciones
A59: Nivel cómodo de reservas | C59: 4 | D59: Meses de importaciones
A60: Fracción de la brecha vs nivel cómodo cerrada vía tipo de cambio | C60: 0.5 | D60: Regla de flotación administrada
A61: Propensión a importar del impulso fiscal | C61: 0.35 | D61: Déficits gemelos: cada punto de desliz fiscal eleva import.
... A77: Balance primario SPNF 2025 | C77: -0.078 | D77: Estimación
A79: Escenarios: parámetros de choque (se aplican desde 2027)
A80: # | B80: Escenario | C80: Shock nivel precios metales preciosos y oro | D80: Shock nivel metales base | E80: Shock nivel petróleo | F80: Declinación extra vol. gas (pp/año) | G80: Desliz fiscal (pp PIB, bal. primario) | H80: Shock crecimiento 2027-28 (pp) | I80: Ajuste TCR 2027-29 (pp/año) | J80: Shock flujos privados (USD mm M/año) | K80: Multiplicador IED | L80: Reperfilamiento (1 = sí) | M80: Retorno de subsidio (fracción import. comb.) | N80: Pasivos contingentes 2027 (% PIB)
A81: 1 | B81: Base | C81: 0 | D81: 0 | E81: 0 | F81: 0 | G81: 0 | H81: 0 | I81: 0 | J81: 0 | K81: 1 | L81: 0 | M81: 0 | N81: 0
A82: 2 | B82: Réplica FMI (TCR que replica su sendero) | C82: 0 | D82: 0 | E82: 0 | F82: 0 | G82: 0 | H82: 0 | I82: -0.0388 | J82: 0 | K82: 1 | L82: 0 | M82: 0 | N82: 0
A83: 3 | B83: Reversión de metales preciosos | C83: -0.35 | D83: -0.1 | E83: 0 | F83: 0 | G83: 0 | H83: -0.01 | I83: 0 | J83: 0 | K83: 1 | L83: 0 | M83: 0 | N83: 0
A84: 4 | B84: Declive acelerado del gas + petróleo caro | C84: 0 | D84: 0 | E84: 0.25 | F84: -0.1 | G84: 0 | H84: 0 | I84: 0 | J84: 0 | K84: 1 | L84: 0 | M84: 0.15 | N84: 0
A85: 5 | B85: Desliz fiscal (-2 pp PIB) | C85: 0 | D85: 0 | E85: 0 | F85: 0 | G85: -0.02 | H85: 0 | I85: 0 | J85: 0 | K85: 1 | L85: 0 | M85: 0 | N85: 0
A86: 6 | B86: Salida de capitales / menos IED | C86: 0 | D86: 0 | E86: 0 | F86: 0 | G86: 0 | H86: 0 | I86: 0 | J86: -0.8 | K86: 0.5 | L86: 0 | M86: 0 | N86: 0
A87: 7 | B87: Combinado (tormenta) | C87: -0.25 | D87: -0.1 | E87: 0 | F87: -0.05 | G87: -0.01 | H87: -0.01 | I87: 0 | J87: -0.4 | K87: 0.7 | L87: 0 | M87: 0 | N87: 0.03
A88: 8 | B88: Base + reperfilamiento bilateral/bonos | C88: 0 | D88: 0 | E88: 0 | F88: 0 | G88: 0 | H88: 0 | I88: 0 | J88: 0 | K88: 1 | L88: 1 | M88: 0 | N88: 0
A89: ► | B89: Escenario activo (según Portada) | C89: =INDEX(C$81:C$88,Portada!$C$6) -> 0 | D89: =INDEX(D$81:D$88,Portada!$C$6) -> 0 | E89: =INDEX(E$81:E$88,Portada!$C$6) -> 0 | F89: =INDEX(F$81:F$88,Portada!$C$6) -> 0 | G89: =INDEX(G$81:G$88,Portada!$C$6) -> 0 | H89: =INDEX(H$81:H$88,Portada!$C$6) -> 0 | I89: =INDEX(I$81:I$88,Portada!$C$6) -> 0 | J89: =INDEX(J$81:J$88,Portada!$C$6) -> 0 | ... N89: =INDEX(N$81:N$88,Portada!$C$6) -> 0

Sheet Externo
A1: Bloque externo: balanza de pagos, reservas y ajuste cambiario
A2: USD miles de millones salvo indicación. La brecha frente al nivel cómodo/piso de reservas se cierra con depreciación endógena, que retroalimenta deuda, crecimiento e inflación (hoja Fiscal_Deuda).
C3: dato | D3: estim.
A4: Concepto | B4: Unidad | C4: 2025 | D4: 2026 | E4: 2027 | F4: 2028 | G4: 2029 | H4: 2030 | I4: 2031 | J4: 2032 | K4: 2033 | L4: 2034 | M4: 2035 | N4: Nota / fuente
A5: Precios efectivos (escenario activo)
A6: Precios metales preciosos | B6: índice | C6: =Supuestos!C12 -> 100 | D6: =Supuestos!D12 -> 175 | E6: =Supuestos!E12*(1+Supuestos!$C$89) -> 161 | F6: =Supuestos!F12*(1+Supuestos!$C$89) -> 153 | G6: =Supuestos!G12*(1+Supuestos!$C$89) -> 153 | H6: =Supuestos!H12*(1+Supuestos!$C$89) -> 153 | I6: =Supuestos!I12*(1+Supuestos!$C$89) -> 153 | J6: =Supuestos!J12*(1+Supuestos!$C$89) -> 153 | K6: =Supuestos!K12*(1+Supuestos!$C$89) -> 153 | L6: =Supuestos!L12*(1+Supuestos!$C$89) -> 153 | M6: =Supuestos!M12*(1+Supuestos!$C$89) -> 153
A7: Precios metales base | B7: índice | C7: =Supuestos!C13 -> 100 | D7: =Supuestos!D13 -> 115 | E7: =Supuestos!E13*(1+Supuestos!$D$89) -> 115 | F7: =Supuestos!F13*(1+Supuestos!$D$89) -> 115 | G7: =Supuestos!G13*(1+Supuestos!$D$89) -> 115 | H7: =Supuestos!H13*(1+Supuestos!$D$89) -> 115 | I7: =Supuestos!I13*(1+Supuestos!$D$89) -> 115 | J7: =Supuestos!J13*(1+Supuestos!$D$89) -> 115 | K7: =Supuestos!K13*(1+Supuestos!$D$89) -> 115 | L7: =Supuestos!L13*(1+Supuestos!$D$89) -> 115 | M7: =Supuestos!M13*(1+Supuestos!$D$89) -> 115
A8: Precio petróleo | B8: índice | C8: =Supuestos!C14 -> 100 | D8: =Supuestos!D14 -> 112 | E8: =Supuestos!E14*(1+Supuestos!$E$89) -> 100 | F8: =Supuestos!F14*(1+Supuestos!$E$89) -> 97 | G8: =Supuestos!G14*(1+Supuestos!$E$89) -> 97 | H8: =Supuestos!H14*(1+Supuestos!$E$89) -> 97 | I8: =Supuestos!I14*(1+Supuestos!$E$89) -> 97 | J8: =Supuestos!J14*(1+Supuestos!$E$89) -> 97 | K8: =Supuestos!K14*(1+Supuestos!$E$89) -> 97 | L8: =Supuestos!L14*(1+Supuestos!$E$89) -> 97 | M8: =Supuestos!M14*(1+Supuestos!$E$89) -> 97
A9: Precio oro | B9: índice | C9: =Supuestos!C15 -> 100 | D9: =Supuestos!D15 -> 140 | E9: =Supuestos!E15*(1+Supuestos!$C$89) -> 129 | F9: =Supuestos!F15*(1+Supuestos!$C$89) -> 122 | G9: =Supuestos!G15*(1+Supuestos!$C$89) -> 122 | H9: =Supuestos!H15*(1+Supuestos!$C$89) -> 122 | I9: =Supuestos!I15*(1+Supuestos!$C$89) -> 122 | J9: =Supuestos!J15*(1+Supuestos!$C$89) -> 122 | K9: =Supuestos!K15*(1+Supuestos!$C$89) -> 122 | L9: =Supuestos!L15*(1+Supuestos!$C$89) -> 122 | M9: =Supuestos!M15*(1+Supuestos!$C$89) -> 122
A10: Var. TCR exógena | B10: % | D10: =Supuestos!D9 -> 0 | E10: =Supuestos!E9+Supuestos!$I$89 -> -0.03 | F10: =Supuestos!F9+Supuestos!$I$89 -> -0.02 | G10: =Supuestos!G9+Supuestos!$I$89 -> -0.01 | H10: =Supuestos!H9 -> 0 | I10: =Supuestos!I9 -> 0 | J10: =Supuestos!J9 -> 0 | K10: =Supuestos!K9 -> 0 | L10: =Supuestos!L9 -> 0 | M10: =Supuestos!M9 -> 0
A11: Depreciación real efectiva (incl. rezago de ajuste) | B11: % | D11: =D10+(1-Supuestos!$C$57)*C45 -> 0 | E11: =E10+(1-Supuestos!$C$57)*D45 -> -0.03 | F11: =F10+(1-Supuestos!$C$57)*E45 -> -0.02 | G11: =G10+(1-Supuestos!$C$57)*F45 -> -0.01 | H11: =H10+(1-Supuestos!$C$57)*G45 -> 0 | I11: =I10+(1-Supuestos!$C$57)*H45 -> 0 | J11: =J10+(1-Supuestos!$C$57)*I45 -> 0 | K11: =K10+(1-Supuestos!$C$57)*J45 -> 0 | ... M11: =M10+(1-Supuestos!$C$57)*L45 -> 0.077293655
A12: Crecimiento real antes del ajuste externo | B12: % | C12: =Supuestos!C6 -> -0.016 | D12: =Supuestos!D6 -> -0.03 | E12: =Supuestos!E6+Supuestos!$H$89 -> -0.015 | F12: =Supuestos!F6+Supuestos!$H$89 -> 0.005 | G12: =Supuestos!G6 -> 0.02 | H12: =Supuestos!H6 -> 0.025 | I12: =Supuestos!I6 -> 0.028 | J12: =Supuestos!J6 -> 0.028 | K12: =Supuestos!K6 -> 0.028 | L12: =Supuestos!L6 -> 0.028 | M12: =Supuestos!M6 -> 0.028
A13: Cuenta corriente (USD miles de millones)
A14: Export. metales preciosos | B14: USD mm M | C14: =Supuestos!C24 -> 2.8 | D14: =Supuestos!D24 -> 6.6 | E14: =D14*E6/D6*(1+Supuestos!E18) -> 6.19344 | F14: =E14*F6/E6*(1+Supuestos!F18) -> 6.0034053 | G14: =F14*G6/F6*(1+Supuestos!G18) -> 6.1234734 | H14: =G14*H6/G6*(1+Supuestos!H18) -> 6.2459428 | I14: =H14*I6/H6*(1+Supuestos!I18) -> 6.3708617 | J14: =I14*J6/I6*(1+Supuestos!J18) -> 6.4982789 | K14: =J14*K6/J6*(1+Supuestos!K18) -> 6.6282445 | L14: =K14*L6/K6*(1+Supuestos!L18) -> 6.7608094 | M14: =L14*M6/L6*(1+Supuestos!M18) -> 6.8960256
A15: Export. metales base | B15: USD mm M | C15: =Supuestos!C25 -> 2.2 | D15: =Supuestos!D25 -> 2.7 | E15: =D15*E7/D7*(1+Supuestos!E19) -> 2.727 | F15: =E15*F7/E7*(1+Supuestos!F19) -> 2.75427 | G15: =F15*G7/F7*(1+Supuestos!G19) -> 2.7818127 | H15: =G15*H7/G7*(1+Supuestos!H19) -> 2.8096308 | I15: =H15*I7/H7*(1+Supuestos!I19) -> 2.8377271 | J15: =I15*J7/I7*(1+Supuestos!J19) -> 2.8661044 | K15: =J15*K7/J7*(1+Supuestos!K19) -> 2.8947655 | L15: =K15*L7/K7*(1+Supuestos!L19) -> 2.9237131 | M15: =L15*M7/L7*(1+Supuestos!M19) -> 2.9529502
A16: Export. hidrocarburos | B16: USD mm M | C16: =Supuestos!C26 -> 1.6 | D16: =Supuestos!D26 -> 1 | E16: =D16*D8/C8*(1+Supuestos!E20+Supuestos!$F$89) -> 0.9856 | F16: =E16*E8/D8*(1+Supuestos!F20+Supuestos!$F$89) -> 0.7744 | G16: =F16*F8/E8*(1+Supuestos!G20+Supuestos!$F$89) -> 0.66102784 | H16: =G16*G8/F8*(1+Supuestos!H20+Supuestos!$F$89) -> 0.5817045 | I16: =H16*H8/G8*(1+Supuestos!I20+Supuestos!$F$89) -> 0.54680223 | J16: =I16*I8/H8*(1+Supuestos!J20+Supuestos!$F$89) -> 0.5139941 | K16: =J16*J8/I8*(1+Supuestos!K20+Supuestos!$F$89) -> 0.48315445 | L16: =K16*K8/J8*(1+Supuestos!L20+Supuestos!$F$89) -> 0.45416518 | M16: =L16*L8/K8*(1+Supuestos!M20+Supuestos!$F$89) -> 0.42691527
A17: Export. agro | B17: USD mm M | C17: =Supuestos!C27 -> 1.9 | D17: =Supuestos!D27 -> 2.2 | E17: =D17*(1+Supuestos!E16)*(1+Supuestos!E21) -> 2.266 | F17: =E17*(1+Supuestos!F16)*(1+Supuestos!F21) -> 2.33398 | G17: =F17*(1+Supuestos!G16)*(1+Supuestos!G21) -> 2.4039994 | H17: =G17*(1+Supuestos!H16)*(1+Supuestos!H21) -> 2.4761194 | I17: =H17*(1+Supuestos!I16)*(1+Supuestos!I21) -> 2.550403 | J17: =I17*(1+Supuestos!J16)*(1+Supuestos!J21) -> 2.6269151 | K17: =J17*(1+Supuestos!K16)*(1+Supuestos!K21) -> 2.7057225 | L17: =K17*(1+Supuestos!L16)*(1+Supuestos!L21) -> 2.7868942 | M17: =L17*(1+Supuestos!M16)*(1+Supuestos!M21) -> 2.870501
A18: Export. resto | B18: USD mm M | C18: =Supuestos!C28 -> 1 | D18: =Supuestos!D28 -> 1.1 | E18: =D18*(1+Supuestos!$C$63)*(1+Supuestos!$C$52*E11) -> 1.1322575 | F18: =E18*(1+Supuestos!$C$63)*(1+Supuestos!$C$52*F11) -> 1.171377 | G18: =F18*(1+Supuestos!$C$63)*(1+Supuestos!$C$52*G11) -> 1.2179685 | H18: =G18*(1+Supuestos!$C$63)*(1+Supuestos!$C$52*H11) -> 1.2727771 | I18: =H18*(1+Supuestos!$C$63)*(1+Supuestos!$C$52*I11) -> 1.3300521 | J18: =I18*(1+Supuestos!$C$63)*(1+Supuestos!$C$52*J11) -> 1.3899044 | K18: =J18*(1+Supuestos!$C$63)*(1+Supuestos!$C$52*K11) -> 1.4524501 | L18: =K18*(1+Supuestos!$C$63)*(1+Supuestos!$C$52*L11) -> 1.5335522 | M18: =L18*(1+Supuestos!$C$63)*(1+Supuestos!$C$52*M11) -> 1.664496
A19: Exportaciones de bienes | B19: USD mm M | C19: =SUM(C14:C18) -> 9.5 | D19: =SUM(D14:D18) -> 13.6 | E19: =SUM(E14:E18) -> 13.304298 | F19: =SUM(F14:F18) -> 13.037432 | G19: =SUM(G14:G18) -> 13.188282 | H19: =SUM(H14:H18) -> 13.386175 | I19: =SUM(I14:I18) -> 13.635846 | J19: =SUM(J14:J18) -> 13.895197 | ... M19: =SUM(M14:M18) -> 14.810888
A20: Import. combustibles | B20: USD mm M | C20: =Supuestos!C29 -> 2.8 | D20: =Supuestos!D29 -> 2.8 | E20: =D20*E8/D8*(1+Supuestos!E22) -> 2.4 | F20: =E20*F8/E8*(1+Supuestos!F22) -> 2.37456 | G20: =F20*G8/F8*(1+Supuestos!G22) -> 2.4220512 | H20: =G20*H8/G8*(1+Supuestos!H22) -> 2.4704922 | I20: =H20*I8/H8*(1+Supuestos!I22) -> 2.5199021 | J20: =I20*J8/I8*(1+Supuestos!J22) -> 2.5703001 | K20: =J20*K8/J8*(1+Supuestos!K22) -> 2.6217061 | L20: =K20*L8/K8*(1+Supuestos!L22) -> 2.6741402 | M20: =L20*M8/L8*(1+Supuestos!M22) -> 2.727623
A21: Import. resto antes del ajuste | B21: USD mm M | C21: =Supuestos!C30 -> 6.37 | D21: =Supuestos!D30 -> 8.8 | E21: =D22*(1+Supuestos!$C$62)*(1+Supuestos!$C$54*E12)*(1-Supuestos!$C$53*E11)-Supuestos!$C$61*Supuestos!$G$89*Fiscal_Deuda!D11 -> 9.0259784 | F21: =E22*(1+Supuestos!$C$62)*(1+Supuestos!$C$54*F12)*(1-Supuestos!$C$53*F11)-Supuestos!$C$61*Supuestos!$G$89*Fiscal_Deuda!E11 -> 9.4099247 | G21: =F22*(1+Supuestos!$C$62)*(1+Supuestos!$C$54*G12)*(1-Supuestos!$C$53*G11)-Supuestos!$C$61*Supuestos!$G$89*Fiscal_Deuda!F11 -> 9.907106 | H21: =G22*(1+Supuestos!$C$62)*(1+Supuestos!$C$54*H12)*(1-Supuestos!$C$53*H11)-Supuestos!$C$61*Supuestos!$G$89*Fiscal_Deuda!G11 -> 10.408406 | I21: =H22*(1+Supuestos!$C$62)*(1+Supuestos!$C$54*I12)*(1-Supuestos!$C$53*I11)-Supuestos!$C$61*Supuestos!$G$89*Fiscal_Deuda!H11 -> 10.973291 | J21: =I22*(1+Supuestos!$C$62)*(1+Supuestos!$C$54*J12)*(1-Supuestos!$C$53*J11)-Supuestos!$C$61*Supuestos!$G$89*Fiscal_Deuda!I11 -> 11.568833 | K21: =J22*(1+Supuestos!$C$62)*(1+Supuestos!$C$54*K12)*(1-Supuestos!$C$53*K11)-Supuestos!$C$61*Supuestos!$G$89*Fiscal_Deuda!J11 -> 12.196697 | L21: =K22*(1+Supuestos!$C$62)*(1+Supuestos!$C$54*L12)*(1-Supuestos!$C$53*L11)-Supuestos!$C$61*Supuestos!$G$89*Fiscal_Deuda!K11 -> 12.382959 | M21: =L22*(1+Supuestos!$C$62)*(1+Supuestos!$C$54*M12)*(1-Supuestos!$C$53*M11)-Supuestos!$C$61*Supuestos!$G$89*Fiscal_Deuda!L11 -> 11.301078
A22: Import. resto (después del ajuste) | B22: USD mm M | C22: =C21 -> 6.37 | D22: =D21-D44 -> 8.8 | E22: =E21-E44 -> 9.0259784 | F22: =F21-F44 -> 9.4099247 | G22: =G21-G44 -> 9.907106 | H22: =H21-H44 -> 10.408406 | I22: =I21-I44 -> 10.973291 | J22: =J21-J44 -> 11.568833 | K22: =K21-K44 -> 11.943703 | ... M22: =M21-M44 -> 10.878088
A23: Importaciones de bienes | B23: USD mm M | C23: =C20+C22 -> 9.17 | D23: =D20+D22 -> 11.6 | E23: =E20+E22 -> 11.425978 | F23: =F20+F22 -> 11.784485 | G23: =G20+G22 -> 12.329157 | H23: =H20+H22 -> 12.878898 | I23: =I20+I22 -> 13.493193 | J23: =J20+J22 -> 14.139133 | ... M23: =M20+M22 -> 13.605711
A24: Servicios (neto) | B24: USD mm M | C24: =Supuestos!C31 -> -1.5 | D24: =Supuestos!D31 -> -1.4 | E24: =D24*(1+Supuestos!$C$62) -> -1.428 | F24: =E24*(1+Supuestos!$C$62) -> -1.45656 | G24: =F24*(1+Supuestos!$C$62) -> -1.4856912 | H24: =G24*(1+Supuestos!$C$62) -> -1.515405 | I24: =H24*(1+Supuestos!$C$62) -> -1.5457131 | J24: =I24*(1+Supuestos!$C$62) -> -1.5766274 | K24: =J24*(1+Supuestos!$C$62) -> -1.6081599 | L24: =K24*(1+Supuestos!$C$62) -> -1.6403231 | M24: =L24*(1+Supuestos!$C$62) -> -1.6731296
A25: Utilidades remitidas (extractivas) | B25: USD mm M | C25: =-Supuestos!$C$64*(C14+C15+C16) -> -0.396 | D25: =-Supuestos!$C$64*(D14+D15+D16) -> -0.618 | E25: =-Supuestos!$C$64*(E14+E15+E16) -> -0.5943624 | F25: =-Supuestos!$C$64*(F14+F15+F16) -> -0.57192452 | G25: =-Supuestos!$C$64*(G14+G15+G16) -> -0.57397883 | H25: =-Supuestos!$C$64*(H14+H15+H16) -> -0.57823669 | I25: =-Supuestos!$C$64*(I14+I15+I16) -> -0.58532346 | J25: =-Supuestos!$C$64*(J14+J15+J16) -> -0.59270265 | ... M25: =-Supuestos!$C$64*(M14+M15+M16) -> -0.61655347
A26: Intereses deuda externa pública | B26: USD mm M | C26: =-Supuestos!C45*Fiscal_Deuda!C25 -> -0.63738 | D26: =-Supuestos!D45*Fiscal_Deuda!C25 -> -0.7082 | E26: =-Supuestos!E45*Fiscal_Deuda!D25 -> -0.770328 | F26: =-Supuestos!F45*Fiscal_Deuda!E25 -> -0.819728 | G26: =-Supuestos!G45*Fiscal_Deuda!F25 -> -0.850928 | H26: =-Supuestos!H45*Fiscal_Deuda!G25 -> -0.874328 | I26: =-Supuestos!I45*Fiscal_Deuda!H25 -> -0.874328 | J26: =-Supuestos!J45*Fiscal_Deuda!I25 -> -0.884728 | K26: =-Supuestos!K45*Fiscal_Deuda!J25 -> -0.895128 | ... M26: =-Supuestos!M45*Fiscal_Deuda!L25 -> -0.910728
A27: Cargos FMI | B27: USD mm M | C27: 0 | D27: =-Supuestos!$C$66*C37 -> 0 | E27: =-Supuestos!$C$66*D37 -> -0.02365 | F27: =-Supuestos!$C$66*E37 -> -0.05775 | G27: =-Supuestos!$C$66*F37 -> -0.09185 | H27: =-Supuestos!$C$66*G37 -> -0.1045 | I27: =-Supuestos!$C$66*H37 -> -0.1045 | J27: =-Supuestos!$C$66*I37 -> -0.10055833 | K27: =-Supuestos!$C$66*J37 -> -0.090933333 | ... M27: =-Supuestos!$C$66*L37 -> -0.058208333
A28: Ingreso secundario (remesas) | B28: USD mm M | C28: =Supuestos!C32 -> 1.05 | D28: =Supuestos!D32 -> 1.35 | E28: =D28*(1+Supuestos!$C$65) -> 1.3905 | F28: =E28*(1+Supuestos!$C$65) -> 1.432215 | G28: =F28*(1+Supuestos!$C$65) -> 1.4751815 | H28: =G28*(1+Supuestos!$C$65) -> 1.5194369 | I28: =H28*(1+Supuestos!$C$65) -> 1.56502 | J28: =I28*(1+Supuestos!$C$65) -> 1.6119706 | K28: =J28*(1+Supuestos!$C$65) -> 1.6603297 | L28: =K28*(1+Supuestos!$C$65) -> 1.7101396 | M28: =L28*(1+Supuestos!$C$65) -> 1.7614438
A29: Cuenta corriente antes del ajuste | B29: USD mm M | D29: =D19-D20-D21+D24+D25+D26+D27+D28 -> 0.6238 | E29: =E19-E20-E21+E24+E25+E26+E27+E28 -> 0.45247873 | F29: =F19-F20-F21+F24+F25+F26+F27+F28 -> -0.22079998 | G29: =G19-G20-G21+G24+G25+G26+G27+G28 -> -0.66814196 | H29: =H19-H20-H21+H24+H25+H26+H27+H28 -> -1.045756 | I29: =I19-I20-I21+I24+I25+I26+I27+I28 -> -1.4021911 | J29: =J19-J20-J21+J24+J25+J26+J27+J28 -> -1.786582 | K29: =K19-K20-K21+K24+K25+K26+K27+K28 -> -2.1883272 | ... M29: =M19-M20-M21+M24+M25+M26+M27+M28 -> -0.71498844
A30: Cuenta corriente | B30: USD mm M | C30: =C19-C23+C24+C25+C26+C27+C28 -> -1.15338 | D30: =D29+D44 -> 0.6238 | E30: =E29+E44 -> 0.45247873 | F30: =F29+F44 -> -0.22079998 | G30: =G29+G44 -> -0.66814196 | H30: =H29+H44 -> -1.045756 | I30: =I29+I44 -> -1.4021911 | J30: =J29+J44 -> -1.786582 | K30: =K29+K44 -> -1.9353337 | ... M30: =M29+M44 -> -0.2919985
A31: Cuenta financiera y reservas (USD miles de millones)
A32: IED neta | B32: USD mm M | C32: =Supuestos!C34 -> 0.1 | D32: =Supuestos!D34 -> 0.3 | E32: =Supuestos!E34*Supuestos!$K$89 -> 0.5 | F32: =Supuestos!F34*Supuestos!$K$89 -> 0.7 | G32: =Supuestos!G34*Supuestos!$K$89 -> 0.9 | H32: =Supuestos!H34*Supuestos!$K$89 -> 1 | I32: =Supuestos!I34*Supuestos!$K$89 -> 1 | J32: =Supuestos!J34*Supuestos!$K$89 -> 1 | K32: =Supuestos!K34*Supuestos!$K$89 -> 1 | L32: =Supuestos!L34*Supuestos!$K$89 -> 1 | M32: =Supuestos!M34*Supuestos!$K$89 -> 1
A33: Desembolsos deuda externa pública | B33: USD mm M | C33: =Supuestos!C35 -> 1.3 | D33: =Supuestos!D35 -> 1.6 | E33: =Supuestos!E35 -> 2 | F33: =Supuestos!F35 -> 1.7 | G33: =Supuestos!G35 -> 1.5 | H33: =Supuestos!H35 -> 1.3 | I33: =Supuestos!I35 -> 1.3 | J33: =Supuestos!J35 -> 1.3 | ... M33: =Supuestos!M35 -> 1.3
A34: Amortizaciones deuda externa pública | B34: USD mm M | C34: =Supuestos!C36 -> 1 | D34: =Supuestos!D36+Supuestos!$L$89*(Supuestos!D38-Supuestos!D37) -> 0.95 | E34: =Supuestos!E36+Supuestos!$L$89*(Supuestos!E38-Supuestos!E37) -> 1.05 | F34: =Supuestos!F36+Supuestos!$L$89*(Supuestos!F38-Supuestos!F37) -> 1.1 | G34: =Supuestos!G36+Supuestos!$L$89*(Supuestos!G38-Supuestos!G37) -> 1.05 | H34: =Supuestos!H36+Supuestos!$L$89*(Supuestos!H38-Supuestos!H37) -> 1.3 | I34: =Supuestos!I36+Supuestos!$L$89*(Supuestos!I38-Supuestos!I37) -> 1.1 | J34: =Supuestos!J36+Supuestos!$L$89*(Supuestos!J38-Supuestos!J37) -> 1.1 | K34: =Supuestos!K36+Supuestos!$L$89*(Supuestos!K38-Supuestos!K37) -> 1.15 | ... M34: =Supuestos!M36+Supuestos!$L$89*(Supuestos!M38-Supuestos!M37) -> 1.2
A35: Desembolsos FMI | B35: USD mm M | C35: =Supuestos!C39 -> 0 | D35: =Supuestos!D39 -> 0.43 | E35: =Supuestos!E39 -> 0.62 | F35: =Supuestos!F39 -> 0.62 | G35: =Supuestos!G39 -> 0.23 | H35: =Supuestos!H39 -> 0 | I35: =Supuestos!I39 -> 0 | J35: =Supuestos!J39 -> 0 | ... M35: =Supuestos!M39 -> 0
A36: Recompras FMI (4,5-10 años) | B36: USD mm M | C36: 0 | D36: 0 | E36: 0 | F36: 0 | G36: 0 | H36: =(Supuestos!C39)/6 -> 0 | I36: =(Supuestos!D39+Supuestos!C39)/6 -> 0.071666667 | J36: =(Supuestos!E39+Supuestos!D39+Supuestos!C39)/6 -> 0.175 | K36: =(Supuestos!F39+Supuestos!E39+Supuestos!D39+Supuestos!C39)/6 -> 0.27833333 | L36: =(Supuestos!G39+Supuestos!F39+Supuestos!E39+Supuestos!D39+Supuestos!C39)/6 -> 0.31666667 | M36: =(Supuestos!H39+Supuestos!G39+Supuestos!F39+Supuestos!E39+Supuestos!D39+Supuestos!C39)/6 -> 0.31666667
A37: Crédito FMI vigente | B37: USD mm M | C37: =Supuestos!$C$76 -> 0 | D37: =C37+D35-D36 -> 0.43 | E37: =D37+E35-E36 -> 1.05 | F37: =E37+F35-F36 -> 1.67 | G37: =F37+G35-G36 -> 1.9 | H37: =G37+H35-H36 -> 1.9 | I37: =H37+I35-I36 -> 1.8283333 | J37: =I37+J35-J36 -> 1.6533333 | K37: =J37+K35-K36 -> 1.375 | ... M37: =L37+M35-M36 -> 0.74166667
A38: Otros flujos privados netos | B38: USD mm M | C38: =Supuestos!C40 -> -1.6 | D38: =Supuestos!D40 -> -1.5 | E38: =Supuestos!E40+Supuestos!$J$89 -> -0.9 | F38: =Supuestos!F40+Supuestos!$J$89 -> -0.6 | G38: =Supuestos!G40+Supuestos!$J$89 -> -0.4 | H38: =Supuestos!H40+Supuestos!$J$89 -> -0.3 | I38: =Supuestos!I40+Supuestos!$J$89 -> -0.3 | J38: =Supuestos!J40+Supuestos!$J$89 -> -0.3 | K38: =Supuestos!K40+Supuestos!$J$89 -> -0.3 | L38: =Supuestos!L40+Supuestos!$J$89 -> -0.3 | M38: =Supuestos!M40+Supuestos!$J$89 -> -0.3
A39: Reservas en oro (valuación) | B39: USD mm M | C39: =Supuestos!$C$73 -> 2.2 | D39: =C39*D9/C9 -> 3.08 | E39: =D39*E9/D9 -> 2.838 | F39: =E39*F9/E9 -> 2.684 | G39: =F39*G9/F9 -> 2.684 | H39: =G39*H9/G9 -> 2.684 | I39: =H39*I9/H9 -> 2.684 | J39: =I39*J9/I9 -> 2.684 | K39: =J39*K9/J9 -> 2.684 | ... M39: =L39*M9/L9 -> 2.684
A40: Reservas no-oro antes del ajuste | B40: USD mm M | C40: =Supuestos!$C$74 -> 1.61 | D40: =C46-C39+D29+D32+D33-D34+D35-D36+D38 -> 2.1138 | E40: =D46-D39+E29+E32+E33-E34+E35-E36+E38 -> 3.7362787 | F40: =E46-E39+F29+F32+F33-F34+F35-F36+F38 -> 4.8354788 | G40: =F46-F39+G29+G32+G33-G34+G35-G36+G38 -> 5.3473368 | H40: =G46-G39+H29+H32+H33-H34+H35-H36+H38 -> 5.0015808 | I40: =H46-H39+I29+I32+I33-I34+I35-I36+I38 -> 4.4277231 | J40: =I46-I39+J29+J32+J33-J34+J35-J36+J38 -> 3.3661411 | K40: =J46-J39+K29+K32+K33-K34+K35-K36+K38 -> 1.7494806 | ... M40: =L46-L39+M29+M32+M33-M34+M35-M36+M38 -> 1.1462537
A41: Reservas antes del ajuste | B41: USD mm M | D41: =D40+D39 -> 5.1938 | E41: =E40+E39 -> 6.5742787 | F41: =F40+F39 -> 7.5194788 | G41: =G40+G39 -> 8.0313368 | H41: =H40+H39 -> 7.6855808 | I41: =I40+I39 -> 7.1117231 | J41: =J40+J39 -> 6.0501411 | K41: =K40+K39 -> 4.4334806 | ... M41: =M40+M39 -> 3.8302537
A42: Piso duro de reservas | B42: USD mm M | D42: =Supuestos!$C$58/12*(D20+D21) -> 2.4166667 | E42: =Supuestos!$C$58/12*(E20+E21) -> 2.3804122 | F42: =Supuestos!$C$58/12*(F20+F21) -> 2.455101 | G42: =Supuestos!$C$58/12*(G20+G21) -> 2.5685744 | H42: =Supuestos!$C$58/12*(H20+H21) -> 2.6831037 | I42: =Supuestos!$C$58/12*(I20+I21) -> 2.8110818 | J42: =Supuestos!$C$58/12*(J20+J21) -> 2.9456527 | K42: =Supuestos!$C$58/12*(K20+K21) -> 3.0871672 | ... M42: =Supuestos!$C$58/12*(M20+M21) -> 2.922646
A43: Nivel cómodo de reservas | B43: USD mm M | D43: =Supuestos!$C$59/12*(D20+D21) -> 3.8666667 | E43: =Supuestos!$C$59/12*(E20+E21) -> 3.8086595 | F43: =Supuestos!$C$59/12*(F20+F21) -> 3.9281616 | G43: =Supuestos!$C$59/12*(G20+G21) -> 4.1097191 | H43: =Supuestos!$C$59/12*(H20+H21) -> 4.2929659 | I43: =Supuestos!$C$59/12*(I20+I21) -> 4.4977309 | J43: =Supuestos!$C$59/12*(J20+J21) -> 4.7130444 | K43: =Supuestos!$C$59/12*(K20+K21) -> 4.9394676 | ... M43: =Supuestos!$C$59/12*(M20+M21) -> 4.6762336
A44: Brecha externa cerrada vía tipo de cambio | B44: USD mm M | C44: 0 | D44: 0 | E44: =MAX(0,E42-E41,Supuestos!$C$60*(E43-E41)) -> 0 | F44: =MAX(0,F42-F41,Supuestos!$C$60*(F43-F41)) -> 0 | G44: =MAX(0,G42-G41,Supuestos!$C$60*(G43-G41)) -> 0 | H44: =MAX(0,H42-H41,Supuestos!$C$60*(H43-H41)) -> 0 | I44: =MAX(0,I42-I41,Supuestos!$C$60*(I43-I41)) -> 0 | J44: =MAX(0,J42-J41,Supuestos!$C$60*(J43-J41)) -> 0 | K44: =MAX(0,K42-K41,Supuestos!$C$60*(K43-K41)) -> 0.2529935 | L44: =MAX(0,L42-L41,Supuestos!$C$60*(L43-L41)) -> 0.95712414 | M44: =MAX(0,M42-M41,Supuestos!$C$60*(M43-M41)) -> 0.42298995
A45: Depreciación nominal de ajuste (endógena) | B45: % | C45: 0 | D45: =D44/(Supuestos!$C$55*D21) -> 0 | E45: =E44/(Supuestos!$C$55*E21) -> 0 | F45: =F44/(Supuestos!$C$55*F21) -> 0 | G45: =G44/(Supuestos!$C$55*G21) -> 0 | H45: =H44/(Supuestos!$C$55*H21) -> 0 | I45: =I44/(Supuestos!$C$55*I21) -> 0 | J45: =J44/(Supuestos!$C$55*J21) -> 0 | K45: =K44/(Supuestos!$C$55*K21) -> 0.041485577 | ... M45: =M44/(Supuestos!$C$55*M21) -> 0.074858337
A46: Reservas internacionales brutas | B46: USD mm M | C46: =C39+C40 -> 3.81 | D46: =D41+D44 -> 5.1938 | E46: =E41+E44 -> 6.5742787 | F46: =F41+F44 -> 7.5194788 | G46: =G41+G44 -> 8.0313368 | H46: =H41+H44 -> 7.6855808 | I46: =I41+I44 -> 7.1117231 | J46: =J41+J44 -> 6.0501411 | K46: =K41+K44 -> 4.6864741 | ... M46: =M41+M44 -> 4.2532437

Sheet Fiscal_Deuda
A1: Bloque fiscal y dinámica de deuda pública (SPNF)
A2: Bs miles de millones salvo indicación. Ingresos por hidrocarburos y minería, y subsidios a combustibles, dependen del bloque externo y del tipo de cambio.
C3: dato | D3: estim.
A4: Concepto | B4: Unidad | C4: 2025 | D4: 2026 | E4: 2027 | F4: 2028 | G4: 2029 | H4: 2030 | I4: 2031 | J4: 2032 | K4: 2033 | L4: 2034 | M4: 2035 | N4: Nota / fuente
A5: Macro
A6: Crecimiento real | B6: % | C6: =Supuestos!C6 -> -0.016 | D6: =Externo!D12-Supuestos!$C$56*Externo!D45 -> -0.03 | E6: =Externo!E12-Supuestos!$C$56*Externo!E45 -> -0.015 | F6: =Externo!F12-Supuestos!$C$56*Externo!F45 -> 0.005 | G6: =Externo!G12-Supuestos!$C$56*Externo!G45 -> 0.02 | H6: =Externo!H12-Supuestos!$C$56*Externo!H45 -> 0.025 | I6: =Externo!I12-Supuestos!$C$56*Externo!I45 -> 0.028 | J6: =Externo!J12-Supuestos!$C$56*Externo!J45 -> 0.028 | K6: =Externo!K12-Supuestos!$C$56*Externo!K45 -> 0.021777164 | ... M6: =Externo!M12-Supuestos!$C$56*Externo!M45 -> 0.016771249
A7: Deflactor del PIB | B7: % | C7: =Supuestos!C7 -> 0.2 | D7: =Supuestos!D7+Supuestos!$C$57*Externo!D45 -> 0.18 | E7: =Supuestos!E7+Supuestos!$C$57*Externo!E45 -> 0.14 | F7: =Supuestos!F7+Supuestos!$C$57*Externo!F45 -> 0.09 | G7: =Supuestos!G7+Supuestos!$C$57*Externo!G45 -> 0.06 | H7: =Supuestos!H7+Supuestos!$C$57*Externo!H45 -> 0.05 | I7: =Supuestos!I7+Supuestos!$C$57*Externo!I45 -> 0.04 | J7: =Supuestos!J7+Supuestos!$C$57*Externo!J45 -> 0.04 | K7: =Supuestos!K7+Supuestos!$C$57*Externo!K45 -> 0.060742788 | ... M7: =Supuestos!M7+Supuestos!$C$57*Externo!M45 -> 0.077429169
A8: PIB nominal | B8: Bs mm M | C8: =Supuestos!$C$70 -> 382.8 | D8: =C8*(1+D6)*(1+D7) -> 438.15288 | E8: =D8*(1+E6)*(1+E7) -> 492.00187 | F8: =E8*(1+F6)*(1+F7) -> 538.96345 | G8: =F8*(1+G6)*(1+G7) -> 582.72728 | H8: =G8*(1+H6)*(1+H7) -> 627.16023 | I8: =H8*(1+I6)*(1+I7) -> 670.50955 | J8: =I8*(1+J6)*(1+J7) -> 716.85517 | K8: =J8*(1+K6)*(1+K7) -> 776.95828 | ... M8: =L8*(1+M6)*(1+M7) -> 955.56843
A9: Tipo de cambio fin de año | B9: Bs/USD | C9: =Supuestos!C10 -> 6.96 | D9: =Supuestos!D10 -> 11.8 | E9: =D9*(1+Supuestos!E7)/(1+Supuestos!E8)*(1+Externo!E10)*(1+Externo!E45) -> 12.755073 | F9: =E9*(1+Supuestos!F7)/(1+Supuestos!F8)*(1+Externo!F10)*(1+Externo!F45) -> 13.318641 | G9: =F9*(1+Supuestos!G7)/(1+Supuestos!G8)*(1+Externo!G10)*(1+Externo!G45) -> 13.662347 | H9: =G9*(1+Supuestos!H7)/(1+Supuestos!H8)*(1+Externo!H10)*(1+Externo!H45) -> 14.022937 | I9: =H9*(1+Supuestos!I7)/(1+Supuestos!I8)*(1+Externo!I10)*(1+Externo!I45) -> 14.255967 | J9: =I9*(1+Supuestos!J7)/(1+Supuestos!J8)*(1+Externo!J10)*(1+Externo!J45) -> 14.49287 | K9: =J9*(1+Supuestos!K7)/(1+Supuestos!K8)*(1+Externo!K10)*(1+Externo!K45) -> 15.344946 | L9: =K9*(1+Supuestos!L7)/(1+Supuestos!L8)*(1+Externo!L10)*(1+Externo!L45) -> 18.011499 | M9: =L9*(1+Supuestos!M7)/(1+Supuestos!M8)*(1+Externo!M10)*(1+Externo!M45) -> 19.681527
A10: Tipo de cambio promedio | B10: Bs/USD | C10: =C9 -> 6.96 | D10: =(C9+D9)/2 -> 9.38 | E10: =(D9+E9)/2 -> 12.277537 | F10: =(E9+F9)/2 -> 13.036857 | G10: =(F9+G9)/2 -> 13.490494 | H10: =(G9+H9)/2 -> 13.842642 | I10: =(H9+I9)/2 -> 14.139452 | J10: =(I9+J9)/2 -> 14.374419 | K10: =(J9+K9)/2 -> 14.918908 | ... M10: =(L9+M9)/2 -> 18.846513
A11: PIB en dólares | B11: USD mm M | C11: =C8/C10 -> 55 | D11: =D8/D10 -> 46.711394 | E11: =E8/E10 -> 40.073337 | F11: =F8/F10 -> 41.341517 | G11: =G8/G10 -> 43.1954 | H11: =H8/H10 -> 45.306396 | I11: =I8/I10 -> 47.421182 | J11: =J8/J10 -> 49.870202 | ... M11: =M8/M10 -> 50.702665
A12: Sector público no financiero (Bs miles de millones)
A13: Renta hidrocarburífera (vinculada a export.) | B13: Bs mm M | D13: =Supuestos!$C$50*Externo!D16*D10 -> 4.221 | E13: =Supuestos!$C$50*Externo!E16*E10 -> 5.4453331 | F13: =Supuestos!$C$50*Externo!F16*F10 -> 4.5430839 | G13: =Supuestos!$C$50*Externo!G16*G10 -> 4.0129165 | H13: =Supuestos!$C$50*Externo!H16*H10 -> 3.6235473 | I13: =Supuestos!$C$50*Externo!I16*I10 -> 3.4791678 | J13: =Supuestos!$C$50*Externo!J16*J10 -> 3.3247649 | K13: =Supuestos!$C$50*Externo!K16*K10 -> 3.2436616 | ... M13: =Supuestos!$C$50*Externo!M16*M10 -> 3.6206389
A14: Renta minera | B14: Bs mm M | D14: =Supuestos!$C$51*(Externo!D14+Externo!D15)*D10 -> 5.23404 | E14: =Supuestos!$C$51*(Externo!E14+Externo!E15)*E10 -> 6.5712617 | F14: =Supuestos!$C$51*(Externo!F14+Externo!F15)*F10 -> 6.8503536 | G14: =Supuestos!$C$51*(Externo!G14+Externo!G15)*G10 -> 7.2082025 | H14: =Supuestos!$C$51*(Externo!H14+Externo!H15)*H10 -> 7.521184 | I14: =Supuestos!$C$51*(Externo!I14+Externo!I15)*I10 -> 7.8122642 | J14: =Supuestos!$C$51*(Externo!J14+Externo!J15)*J10 -> 8.0764541 | K14: =Supuestos!$C$51*(Externo!K14+Externo!K15)*K10 -> 8.5243746 | ... M14: =Supuestos!$C$51*(Externo!M14+Externo!M15)*M10 -> 11.137131
A15: Subsidio a combustibles | B15: Bs mm M | D15: =Supuestos!D43*Externo!D20*D10 -> 3.9396 | E15: =(Supuestos!E43+Supuestos!$M$89)*Externo!E20*E10 -> 1.4733044 | F15: =(Supuestos!F43+Supuestos!$M$89)*Externo!F20*F10 -> 0 | G15: =(Supuestos!G43+Supuestos!$M$89)*Externo!G20*G10 -> 0 | H15: =(Supuestos!H43+Supuestos!$M$89)*Externo!H20*H10 -> 0 | I15: =(Supuestos!I43+Supuestos!$M$89)*Externo!I20*I10 -> 0 | J15: =(Supuestos!J43+Supuestos!$M$89)*Externo!J20*J10 -> 0 | K15: =(Supuestos!K43+Supuestos!$M$89)*Externo!K20*K10 -> 0 | L15: =(Supuestos!L43+Supuestos!$M$89)*Externo!L20*L10 -> 0 | M15: =(Supuestos!M43+Supuestos!$M$89)*Externo!M20*M10 -> 0
A16: Balance primario no-commodity | B16: % PIB | C16: =Supuestos!C42 -> -0.0715 | D16: =Supuestos!D42 -> -0.0643 | E16: =Supuestos!E42+Supuestos!$G$89 -> -0.0343 | F16: =Supuestos!F42+Supuestos!$G$89 -> -0.0063 | G16: =Supuestos!G42+Supuestos!$G$89 -> 0.0077 | H16: =Supuestos!H42+Supuestos!$G$89 -> 0.007 | I16: =Supuestos!I42+Supuestos!$G$89 -> 0.0043 | J16: =Supuestos!J42+Supuestos!$G$89 -> 0.0041 | K16: =Supuestos!K42+Supuestos!$G$89 -> 0.0034 | L16: =Supuestos!L42+Supuestos!$G$89 -> 0.0019 | M16: =Supuestos!M42+Supuestos!$G$89 -> 0.0015
A17: Balance primario | B17: Bs mm M | C17: =Supuestos!$C$77*C8 -> -29.8584 | D17: =D16*D8+D13+D14-D15 -> -22.65779 | E17: =E16*E8+E13+E14-E15 -> -6.3323737 | F17: =F16*F8+F13+F14-F15 -> 7.9979678 | G17: =G16*G8+G13+G14-G15 -> 15.708119 | H17: =H16*H8+H13+H14-H15 -> 15.534853 | I17: =I16*I8+I13+I14-I15 -> 14.174623 | J17: =J16*J8+J13+J14-J15 -> 14.340325 | K17: =K16*K8+K13+K14-K15 -> 14.409694 | ... M17: =M16*M8+M13+M14-M15 -> 16.191122
A18: Intereses deuda externa | B18: Bs mm M | D18: =Supuestos!D45*C25*D10 -> 6.642916 | E18: =Supuestos!E45*D25*E10 -> 9.4577303 | F18: =Supuestos!F45*E25*F10 -> 10.686677 | G18: =Supuestos!G45*F25*G10 -> 11.479439 | H18: =Supuestos!H45*G25*H10 -> 12.10301 | I18: =Supuestos!I45*H25*I10 -> 12.362519 | J18: =Supuestos!J45*I25*J10 -> 12.717451 | K18: =Supuestos!K45*J25*K10 -> 13.354332 | ... M18: =Supuestos!M45*L25*M10 -> 17.164047
A19: Intereses deuda interna | B19: Bs mm M | D19: =Supuestos!D44*C28 -> 11.016 | E19: =Supuestos!E44*D28 -> 17.174281 | F19: =Supuestos!F44*E28 -> 21.557293 | G19: =Supuestos!G44*F28 -> 22.87362 | H19: =Supuestos!H44*G28 -> 22.277026 | I19: =Supuestos!I44*H28 -> 21.957624 | J19: =Supuestos!J44*I28 -> 23.113563 | K19: =Supuestos!K44*J28 -> 24.354388 | ... M19: =Supuestos!M44*L28 -> 27.717029
A20: Balance global | B20: Bs mm M | C20: =Supuestos!$C$75*C8 -> -43.6392 | D20: =D17-D18-D19 -> -40.316706 | E20: =E17-E18-E19 -> -32.964385 | F20: =F17-F18-F19 -> -24.246002 | G20: =G17-G18-G19 -> -18.64494 | H20: =H17-H18-H19 -> -18.845183 | I20: =I17-I18-I19 -> -20.14552 | J20: =J17-J18-J19 -> -21.490689 | K20: =K17-K18-K19 -> -23.299026 | ... M20: =M17-M18-M19 -> -28.689954
A21: Financiamiento externo neto | B21: Bs mm M | D21: =(Externo!D33-Externo!D34)*D10 -> 6.097 | E21: =(Externo!E33-Externo!E34)*E10 -> 11.66366 | F21: =(Externo!F33-Externo!F34)*F10 -> 7.8221142 | G21: =(Externo!G33-Externo!G34)*G10 -> 6.0707223 | H21: =(Externo!H33-Externo!H34)*H10 -> 0 | I21: =(Externo!I33-Externo!I34)*I10 -> 2.8278905 | J21: =(Externo!J33-Externo!J34)*J10 -> 2.8748838 | K21: =(Externo!K33-Externo!K34)*K10 -> 2.2378362 | ... M21: =(Externo!M33-Externo!M34)*M10 -> 1.8846513
A22: Pasivos contingentes reconocidos | B22: Bs mm M | D22: 0 | E22: =Supuestos!$N$89*E8 -> 0 | F22: 0 | G22: 0 | H22: 0 | I22: 0 | J22: 0 | K22: 0 | L22: 0 | M22: 0
A23: Financiamiento interno | B23: Bs mm M | D23: =-D20-D21+D22 -> 34.219706 | E23: =-E20-E21+E22 -> 21.300725 | F23: =-F20-F21+F22 -> 16.423888 | G23: =-G20-G21+G22 -> 12.574218 | H23: =-H20-H21+H22 -> 18.845183 | I23: =-I20-I21+I22 -> 17.317629 | J23: =-J20-J21+J22 -> 18.615805 | K23: =-K20-K21+K22 -> 21.06119 | ... M23: =-M20-M21+M22 -> 26.805302
A24: Deuda pública SPNF
A25: Deuda externa pública | B25: USD mm M | C25: =Supuestos!$C$71 -> 14.164 | D25: =C25+Externo!D33-Externo!D34 -> 14.814 | E25: =D25+Externo!E33-Externo!E34 -> 15.764 | F25: =E25+Externo!F33-Externo!F34 -> 16.364 | G25: =F25+Externo!G33-Externo!G34 -> 16.814 | H25: =G25+Externo!H33-Externo!H34 -> 16.814 | I25: =H25+Externo!I33-Externo!I34 -> 17.014 | J25: =I25+Externo!J33-Externo!J34 -> 17.214 | K25: =J25+Externo!K33-Externo!K34 -> 17.364 | ... M25: =L25+Externo!M33-Externo!M34 -> 17.614
A26: Deuda interna en USD / indexada | B26: USD mm M | C26: =Supuestos!C47 -> 2 | D26: =Supuestos!D47 -> 2 | E26: =Supuestos!E47 -> 2 | F26: =Supuestos!F47 -> 2 | G26: =Supuestos!G47 -> 2 | H26: =Supuestos!H47 -> 2 | I26: =Supuestos!I47 -> 2 | J26: =Supuestos!J47 -> 2 | ... M26: =Supuestos!M47 -> 2
A27: Deuda interna en moneda local | B27: Bs mm M | C27: =Supuestos!$C$72 -> 206.4 | D27: =C27+D23 -> 240.61971 | E27: =D27+E23 -> 261.92043 | F27: =E27+F23 -> 278.34432 | G27: =F27+G23 -> 290.91854 | H27: =G27+H23 -> 309.76372 | I27: =H27+I23 -> 327.08135 | J27: =I27+J23 -> 345.69715 | K27: =J27+K23 -> 366.75834 | ... M27: =L27+M23 -> 417.19814
A28: Deuda interna total | B28: Bs mm M | C28: =C27+C26*C9 -> 220.32 | D28: =D27+D26*D9 -> 264.21971 | E28: =E27+E26*E9 -> 287.43058 | F28: =F27+F26*F9 -> 304.9816 | G28: =G27+G26*G9 -> 318.24323 | H28: =H27+H26*H9 -> 337.80959 | I28: =I27+I26*I9 -> 355.59328 | J28: =J27+J26*J9 -> 374.6829 | ... M28: =M27+M26*M9 -> 456.56119
A29: Deuda pública total | B29: Bs mm M | C29: =C25*C9+C28 -> 318.90144 | D29: =D25*D9+D28 -> 439.02491 | E29: =E25*E9+E28 -> 488.50155 | F29: =F25*F9+F28 -> 522.92783 | G29: =G25*G9+G28 -> 547.96194 | H29: =H25*H9+H28 -> 573.59126 | I29: =I25*I9+I28 -> 598.14432 | J29: =J25*J9+J28 -> 624.16316 | ... M29: =M25*M9+M28 -> 803.2316
A30: Deuda pública / PIB | B30: % PIB | C30: =C29/C8 -> 0.83307586 | D30: =D29/D8 -> 1.0019902 | E30: =E29/E8 -> 0.99288556 | F30: =F29/F8 -> 0.97024731 | G30: =G29/G8 -> 0.9403403 | H30: =H29/H8 -> 0.91458487 | I30: =I29/I8 -> 0.89207427 | J30: =J29/J8 -> 0.87069633 | ... M30: =M29/M8 -> 0.84057989
A31: Deuda en moneda extranjera o indexada / total | B31: % | C31: =(C25+C26)*C9/C29 -> 0.35277809 | D31: =(D25+D26)*D9/D29 -> 0.45192242 | E31: =(E25+E26)*E9/E29 -> 0.46382887 | F31: =(F25+F26)*F9/F29 -> 0.46771944 | G31: =(G25+G26)*G9/G29 -> 0.46908989 | H31: =(H25+H26)*H9/H29 -> 0.45995739 | I31: =(I25+I26)*I9/I29 -> 0.45317319 | J31: =(J25+J26)*J9/J29 -> 0.44614297 | ... M31: =(M25+M26)*M9/M29 -> 0.48060045
A32: Deuda neta de tenencias del BCB | B32: Bs mm M | D32: =D29-Supuestos!D46*D27 -> 306.68407 | E32: =E29-Supuestos!E46*E27 -> 349.68373 | F32: =F29-Supuestos!F46*F27 -> 380.97223 | G32: =G29-Supuestos!G46*G27 -> 405.41186 | H32: =H29-Supuestos!H46*H27 -> 428.00231 | I32: =I29-Supuestos!I46*I27 -> 450.95771 | J32: =J29-Supuestos!J46*J27 -> 475.51339 | K32: =K29-Supuestos!K46*K27 -> 513.52696 | ... M32: =M29-Supuestos!M46*M27 -> 648.86829
A33: Deuda neta de BCB / PIB | B33: % PIB | D33: =D32/D8 -> 0.69994763 | E33: =E32/E8 -> 0.71073658 | F33: =F32/F8 -> 0.70686098 | G33: =G32/G8 -> 0.69571457 | H33: =H32/H8 -> 0.68244492 | I33: =I32/I8 -> 0.67255971 | J33: =J32/J8 -> 0.66333258 | K33: =K32/K8 -> 0.66094534 | ... M33: =M32/M8 -> 0.67903907
A34: Amortizaciones deuda interna | B34: Bs mm M | D34: =C28/Supuestos!$C$67 -> 44.064 | E34: =D28/Supuestos!$C$67 -> 52.843941 | F34: =E28/Supuestos!$C$67 -> 57.486116 | G34: =F28/Supuestos!$C$67 -> 60.99632 | H34: =G28/Supuestos!$C$67 -> 63.648646 | I34: =H28/Supuestos!$C$67 -> 67.561919 | J34: =I28/Supuestos!$C$67 -> 71.118657 | K34: =J28/Supuestos!$C$67 -> 74.936579 | ... M34: =L28/Supuestos!$C$67 -> 85.283166
A35: Necesidades brutas de financiamiento | B35: Bs mm M | D35: =-D20+D34+Externo!D34*D10 -> 93.291706 | E35: =-E20+E34+Externo!E34*E10 -> 98.69974 | F35: =-F20+F34+Externo!F34*F10 -> 96.07266 | G35: =-G20+G34+Externo!G34*G10 -> 93.806279 | H35: =-H20+H34+Externo!H34*H10 -> 100.48926 | I35: =-I20+I34+Externo!I34*I10 -> 103.26084 | J35: =-J20+J34+Externo!J34*J10 -> 108.42121 | K35: =-K20+K34+Externo!K34*K10 -> 115.39235 | ... M35: =-M20+M34+Externo!M34*M10 -> 136.58894
A36: NBF / PIB | B36: % PIB | D36: =D35/D8 -> 0.21292044 | E36: =E35/E8 -> 0.20060846 | F36: =F35/F8 -> 0.1782545 | G36: =G35/G8 -> 0.16097801 | H36: =H35/H8 -> 0.16022901 | I36: =I35/I8 -> 0.15400353 | J36: =J35/J8 -> 0.15124562 | K36: =K35/K8 -> 0.14851808 | ... M36: =M35/M8 -> 0.14293998
A37: Balance global / PIB | B37: % PIB | C37: =C20/C8 -> -0.114 | D37: =D20/D8 -> -0.092015157 | E37: =E20/E8 -> -0.067000528 | F37: =F20/F8 -> -0.044986357 | G37: =G20/G8 -> -0.031995997 | H37: =H20/H8 -> -0.030048434 | I37: =I20/I8 -> -0.03004509 | J37: =J20/J8 -> -0.029979123 | ... M37: =M20/M8 -> -0.030023966
A38: Balance primario / PIB | B38: % PIB | C38: =C17/C8 -> -0.078 | D38: =D17/D8 -> -0.051712065 | E38: =E17/E8 -> -0.012870629 | F38: =F17/F8 -> 0.014839537 | G38: =G17/G8 -> 0.02695621 | H38: =H17/H8 -> 0.02477015 | I38: =I17/I8 -> 0.021140076 | J38: =J17/J8 -> 0.020004494 | ... M38: =M17/M8 -> 0.01694397
A39: Descomposición de la variación de deuda/PIB (pp)
A40: Déficit primario | B40: pp | D40: =-D17/D8 -> 0.051712065 | E40: =-E17/E8 -> 0.012870629 | F40: =-F17/F8 -> -0.014839537 | G40: =-G17/G8 -> -0.02695621 | H40: =-H17/H8 -> -0.02477015 | I40: =-I17/I8 -> -0.021140076 | J40: =-J17/J8 -> -0.020004494 | K40: =-K17/K8 -> -0.018546291 | ... M40: =-M17/M8 -> -0.01694397
A41: Intereses | B41: pp | D41: =(D18+D19)/D8 -> 0.040303092 | E41: =(E18+E19)/E8 -> 0.054129898 | F41: =(F18+F19)/F8 -> 0.059825894 | G41: =(G18+G19)/G8 -> 0.058952207 | H41: =(H18+H19)/H8 -> 0.054818584 | I41: =(I18+I19)/I8 -> 0.051185166 | J41: =(J18+J19)/J8 -> 0.049983617 | K41: =(K18+K19)/K8 -> 0.048533778 | ... M41: =(M18+M19)/M8 -> 0.046967935
A42: Crecimiento real | B42: pp | D42: =-C30*D6/((1+D6)*(1+D7)) -> 0.021834943 | E42: =-D30*E6/((1+E6)*(1+E7)) -> 0.013384855 | F42: =-E30*F6/((1+F6)*(1+F7)) -> -0.0045318616 | G42: =-F30*G6/((1+G6)*(1+G7)) -> -0.017947601 | H42: =-G30*H6/((1+H6)*(1+H7)) -> -0.02184298 | I42: =-H30*I6/((1+I6)*(1+I7)) -> -0.023952761 | J42: =-I30*J6/((1+J6)*(1+J7)) -> -0.023363214 | K42: =-J30*K6/((1+K6)*(1+K7)) -> -0.017494508 | ... M42: =-L30*M6/((1+M6)*(1+M7)) -> -0.013020599
A43: Inflación (deflactor) | B43: pp | D43: =-C30*D7*(1+D6)/((1+D6)*(1+D7)) -> -0.12707937 | E43: =-D30*E7*(1+E6)/((1+E6)*(1+E7)) -> -0.12305143 | F43: =-E30*F7*(1+F6)/((1+F6)*(1+F7)) -> -0.081981377 | G43: =-F30*G7*(1+G6)/((1+G6)*(1+G7)) -> -0.054919659 | H43: =-G30*H7*(1+H6)/((1+H6)*(1+H7)) -> -0.044778109 | I43: =-H30*I7*(1+I6)/((1+I6)*(1+I7)) -> -0.035176341 | J43: =-I30*J7*(1+J6)/((1+J6)*(1+J7)) -> -0.034310549 | K43: =-J30*K7*(1+K6)/((1+K6)*(1+K7)) -> -0.049859894 | ... M43: =-L30*M7*(1+M6)/((1+M6)*(1+M7)) -> -0.061121417
A44: Tipo de cambio (revaluación deuda en USD) | B44: pp | D44: =((C25+C26)*(D9-C9)+(Externo!D33-Externo!D34)*(D9-D10)+(D26-C26)*D9)/D8 -> 0.18214364 | E44: =((D25+D26)*(E9-D9)+(Externo!E33-Externo!E34)*(E9-E10)+(E26-D26)*E9)/E8 -> 0.033561382 | F44: =((E25+E26)*(F9-E9)+(Externo!F33-Externo!F34)*(F9-F10)+(F26-E26)*F9)/F8 -> 0.018888626 | G44: =((F25+F26)*(G9-F9)+(Externo!G33-Externo!G34)*(G9-G10)+(G26-F26)*G9)/G8 -> 0.010964249 | H44: =((G25+G26)*(H9-G9)+(Externo!H33-Externo!H34)*(H9-H10)+(H26-G26)*H9)/H8 -> 0.01081723 | I44: =((H25+H26)*(I9-H9)+(Externo!I33-Externo!I34)*(I9-I10)+(I26-H26)*I9)/I8 -> 0.0065734096 | J44: =((I25+I26)*(J9-I9)+(Externo!J33-Externo!J34)*(J9-J10)+(J26-I26)*J9)/J8 -> 0.0063166984 | K44: =((J25+J26)*(K9-J9)+(Externo!K33-Externo!K34)*(K9-K10)+(K26-J26)*K9)/K8 -> 0.021153893 | ... M44: =((L25+L26)*(M9-L9)+(Externo!M33-Externo!M34)*(M9-M10)+(M26-L26)*M9)/M8 -> 0.034191617
A45: Pasivos contingentes | B45: pp | D45: =D22/D8 -> 0 | E45: =E22/E8 -> 0 | F45: =F22/F8 -> 0 | G45: =G22/G8 -> 0 | H45: =H22/H8 -> 0 | I45: =I22/I8 -> 0 | J45: =J22/J8 -> 0 | K45: =K22/K8 -> 0 | ... M45: =M22/M8 -> 0
A46: Residuo (control = 0) | B46: pp | D46: =(D30-C30)-(D40+D41+D42+D43+D44+D45) -> 0 | E46: =(E30-D30)-(E40+E41+E42+E43+E44+E45) -> -1.0408341e-16 | F46: =(F30-E30)-(F40+F41+F42+F43+F44+F45) -> 1.2836954e-16 | G46: =(G30-F30)-(G40+G41+G42+G43+G44+G45) -> -1.2490009e-16 | H46: =(H30-G30)-(H40+H41+H42+H43+H44+H45) -> 1.0408341e-16 | I46: =(I30-H30)-(I40+I41+I42+I43+I44+I45) -> -2.0122792e-16 | J46: =(J30-I30)-(J40+J41+J42+J43+J44+J45) -> 7.6327833e-17 | K46: =(K30-J30)-(K40+K41+K42+K43+K44+K45) -> 2.4980018e-16 | ... M46: =(M30-L30)-(M40+M41+M42+M43+M44+M45) -> 4.8572257e-17
A47: Variación deuda/PIB | B47: pp | D47: =D30-C30 -> 0.16891437 | E47: =E30-D30 -> -0.0091046678 | F47: =F30-E30 -> -0.022638255 | G47: =G30-F30 -> -0.029907015 | H47: =H30-G30 -> -0.025755425 | I47: =I30-H30 -> -0.022510603 | J47: =J30-I30 -> -0.021377942 | K47: =K30-J30 -> -0.016213022 | ... M47: =M30-L30 -> -0.0099264337

Sheet Indicadores
A1: Indicadores de sostenibilidad (escenario activo)
A2: En rojo: valores que superan umbrales de referencia (columna de notas).
C3: dato | D3: estim.
A4: Concepto | B4: Unidad | C4: 2025 | D4: 2026 | E4: 2027 | F4: 2028 | G4: 2029 | H4: 2030 | I4: 2031 | J4: 2032 | K4: 2033 | L4: 2034 | M4: 2035 | N4: Nota / fuente
A5: Solvencia y liquidez fiscal
A6: Deuda pública / PIB | B6: % PIB | C6: =Fiscal_Deuda!C30 -> 0.83307586 | D6: =Fiscal_Deuda!D30 -> 1.0019902 | E6: =Fiscal_Deuda!E30 -> 0.99288556 | F6: =Fiscal_Deuda!F30 -> 0.97024731 | G6: =Fiscal_Deuda!G30 -> 0.9403403 | H6: =Fiscal_Deuda!H30 -> 0.91458487 | I6: =Fiscal_Deuda!I30 -> 0.89207427 | J6: =Fiscal_Deuda!J30 -> 0.87069633 | ... M6: =Fiscal_Deuda!M30 -> 0.84057989 | N6: 70%: umbral de alto escrutinio, marco MAC SRDSF (mercados emergentes)
A7: Deuda neta de tenencias BCB / PIB | B7: % PIB | D7: =Fiscal_Deuda!D33 -> 0.69994763 | E7: =Fiscal_Deuda!E33 -> 0.71073658 | F7: =Fiscal_Deuda!F33 -> 0.70686098 | G7: =Fiscal_Deuda!G33 -> 0.69571457 | H7: =Fiscal_Deuda!H33 -> 0.68244492 | I7: =Fiscal_Deuda!I33 -> 0.67255971 | J7: =Fiscal_Deuda!J33 -> 0.66333258 | K7: =Fiscal_Deuda!K33 -> 0.66094534 | ... M7: =Fiscal_Deuda!M33 -> 0.67903907
A8: NBF / PIB | B8: % PIB | D8: =Fiscal_Deuda!D36 -> 0.21292044 | E8: =Fiscal_Deuda!E36 -> 0.20060846 | F8: =Fiscal_Deuda!F36 -> 0.1782545 | G8: =Fiscal_Deuda!G36 -> 0.16097801 | H8: =Fiscal_Deuda!H36 -> 0.16022901 | I8: =Fiscal_Deuda!I36 -> 0.15400353 | J8: =Fiscal_Deuda!J36 -> 0.15124562 | K8: =Fiscal_Deuda!K36 -> 0.14851808 | ... M8: =Fiscal_Deuda!M36 -> 0.14293998 | N8: 15%: umbral NBF, marco MAC SRDSF
A9: Balance global / PIB | B9: % PIB | C9: =Fiscal_Deuda!C37 -> -0.114 | D9: =Fiscal_Deuda!D37 -> -0.092015157 | E9: =Fiscal_Deuda!E37 -> -0.067000528 | F9: =Fiscal_Deuda!F37 -> -0.044986357 | G9: =Fiscal_Deuda!G37 -> -0.031995997 | H9: =Fiscal_Deuda!H37 -> -0.030048434 | I9: =Fiscal_Deuda!I37 -> -0.03004509 | J9: =Fiscal_Deuda!J37 -> -0.029979123 | ... M9: =Fiscal_Deuda!M37 -> -0.030023966
A10: Deuda en ME o indexada / total | B10: % | C10: =Fiscal_Deuda!C31 -> 0.35277809 | D10: =Fiscal_Deuda!D31 -> 0.45192242 | E10: =Fiscal_Deuda!E31 -> 0.46382887 | F10: =Fiscal_Deuda!F31 -> 0.46771944 | G10: =Fiscal_Deuda!G31 -> 0.46908989 | H10: =Fiscal_Deuda!H31 -> 0.45995739 | I10: =Fiscal_Deuda!I31 -> 0.45317319 | J10: =Fiscal_Deuda!J31 -> 0.44614297 | ... M10: =Fiscal_Deuda!M31 -> 0.48060045 | N10: Referencia: >50% eleva vulnerabilidad cambiaria
A11: Sostenibilidad externa
A12: Deuda externa privada | B12: USD mm M | C12: =Supuestos!$C$69 -> 3 | D12: =Supuestos!$C$69 -> 3 | E12: =D12*Fiscal_Deuda!E11/Fiscal_Deuda!D11 -> 2.5736764 | F12: =E12*Fiscal_Deuda!F11/Fiscal_Deuda!E11 -> 2.6551242 | G12: =F12*Fiscal_Deuda!G11/Fiscal_Deuda!F11 -> 2.7741882 | H12: =G12*Fiscal_Deuda!H11/Fiscal_Deuda!G11 -> 2.9097652 | I12: =H12*Fiscal_Deuda!I11/Fiscal_Deuda!H11 -> 3.0455855 | J12: =I12*Fiscal_Deuda!J11/Fiscal_Deuda!I11 -> 3.2028718 | K12: =J12*Fiscal_Deuda!K11/Fiscal_Deuda!J11 -> 3.3447147 | L12: =K12*Fiscal_Deuda!L11/Fiscal_Deuda!K11 -> 3.3589108 | M12: =L12*Fiscal_Deuda!M11/Fiscal_Deuda!L11 -> 3.256336
A13: Deuda externa total (pública + FMI + privada) | B13: USD mm M | C13: =Fiscal_Deuda!C25+Externo!C37+C12 -> 17.164 | D13: =Fiscal_Deuda!D25+Externo!D37+D12 -> 18.244 | E13: =Fiscal_Deuda!E25+Externo!E37+E12 -> 19.387676 | F13: =Fiscal_Deuda!F25+Externo!F37+F12 -> 20.689124 | G13: =Fiscal_Deuda!G25+Externo!G37+G12 -> 21.488188 | H13: =Fiscal_Deuda!H25+Externo!H37+H12 -> 21.623765 | I13: =Fiscal_Deuda!I25+Externo!I37+I12 -> 21.887919 | J13: =Fiscal_Deuda!J25+Externo!J37+J12 -> 22.070205 | ... M13: =Fiscal_Deuda!M25+Externo!M37+M12 -> 21.612003
A14: Deuda externa total / PIB | B14: % PIB | C14: =C13/Fiscal_Deuda!C11 -> 0.31207273 | D14: =D13/Fiscal_Deuda!D11 -> 0.39056852 | E14: =E13/Fiscal_Deuda!E11 -> 0.48380488 | F14: =F13/Fiscal_Deuda!F11 -> 0.50044424 | G14: =G13/Fiscal_Deuda!G11 -> 0.49746474 | H14: =H13/Fiscal_Deuda!H11 -> 0.47727842 | I14: =I13/Fiscal_Deuda!I11 -> 0.46156417 | J14: =J13/Fiscal_Deuda!J11 -> 0.44255295 | ... M14: =M13/Fiscal_Deuda!M11 -> 0.42624984 | N14: 40%: referencia LIC-DSF (capacidad media, en VP)
A15: Deuda externa total / export. bienes | B15: % | C15: =C13/Externo!C19 -> 1.8067368 | D15: =D13/Externo!D19 -> 1.3414706 | E15: =E13/Externo!E19 -> 1.4572492 | F15: =F13/Externo!F19 -> 1.5869018 | G15: =G13/Externo!G19 -> 1.6293395 | H15: =H13/Externo!H19 -> 1.6153805 | I15: =I13/Externo!I19 -> 1.605175 | J15: =J13/Externo!J19 -> 1.5883334 | ... M15: =M13/Externo!M19 -> 1.4591969 | N15: 180%: referencia LIC-DSF (capacidad media, en VP)
A16: Servicio deuda externa pública + FMI | B16: USD mm M | D16: =-Externo!D26-Externo!D27+Externo!D34+Externo!D36 -> 1.6582 | E16: =-Externo!E26-Externo!E27+Externo!E34+Externo!E36 -> 1.843978 | F16: =-Externo!F26-Externo!F27+Externo!F34+Externo!F36 -> 1.977478 | G16: =-Externo!G26-Externo!G27+Externo!G34+Externo!G36 -> 1.992778 | H16: =-Externo!H26-Externo!H27+Externo!H34+Externo!H36 -> 2.278828 | I16: =-Externo!I26-Externo!I27+Externo!I34+Externo!I36 -> 2.1504947 | J16: =-Externo!J26-Externo!J27+Externo!J34+Externo!J36 -> 2.2602863 | K16: =-Externo!K26-Externo!K27+Externo!K34+Externo!K36 -> 2.4143947 | ... M16: =-Externo!M26-Externo!M27+Externo!M34+Externo!M36 -> 2.485603
A17: Servicio deuda externa / export. bienes | B17: % | D17: =D16/Externo!D19 -> 0.12192647 | E17: =E16/Externo!E19 -> 0.13860018 | F17: =F16/Externo!F19 -> 0.15167695 | G17: =G16/Externo!G19 -> 0.15110217 | H17: =H16/Externo!H19 -> 0.17023743 | I17: =I16/Externo!I19 -> 0.15770893 | J17: =J16/Externo!J19 -> 0.16266674 | K17: =K16/Externo!K19 -> 0.17045589 | ... M17: =M16/Externo!M19 -> 0.16782269 | N17: 15%: referencia LIC-DSF (capacidad media)
A18: Cuenta corriente / PIB | B18: % PIB | C18: =Externo!C30/Fiscal_Deuda!C11 -> -0.020970545 | D18: =Externo!D30/Fiscal_Deuda!D11 -> 0.013354343 | E18: =Externo!E30/Fiscal_Deuda!E11 -> 0.011291266 | F18: =Externo!F30/Fiscal_Deuda!F11 -> -0.0053408774 | G18: =Externo!G30/Fiscal_Deuda!G11 -> -0.015467896 | H18: =Externo!H30/Fiscal_Deuda!H11 -> -0.023081862 | I18: =Externo!I30/Fiscal_Deuda!I11 -> -0.029568877 | J18: =Externo!J30/Fiscal_Deuda!J11 -> -0.035824638 | ... M18: =Externo!M30/Fiscal_Deuda!M11 -> -0.0057590364
A19: Reservas brutas | B19: USD mm M | C19: =Externo!C46 -> 3.81 | D19: =Externo!D46 -> 5.1938 | E19: =Externo!E46 -> 6.5742787 | F19: =Externo!F46 -> 7.5194788 | G19: =Externo!G46 -> 8.0313368 | H19: =Externo!H46 -> 7.6855808 | I19: =Externo!I46 -> 7.1117231 | J19: =Externo!J46 -> 6.0501411 | ... M19: =Externo!M46 -> 4.2532437
A20: Reservas / meses de importación | B20: meses | C20: =Externo!C46/(Externo!C23/12) -> 4.9858233 | D20: =Externo!D46/(Externo!D23/12) -> 5.3728966 | E20: =Externo!E46/(Externo!E23/12) -> 6.9045593 | F20: =Externo!F46/(Externo!F23/12) -> 7.6569954 | G20: =Externo!G46/(Externo!G23/12) -> 7.8169205 | H20: =Externo!H46/(Externo!H23/12) -> 7.1610919 | I20: =Externo!I46/(Externo!I23/12) -> 6.3247209 | J20: =Externo!J46/(Externo!J23/12) -> 5.1348052 | ... M20: =Externo!M46/(Externo!M23/12) -> 3.7512868 | N20: 3 meses de importaciones
A21: Reservas / vencimientos externos del año (Greenspan-Guidotti) | B21: x | D21: =Externo!D46/(Externo!D34+Externo!D36+Supuestos!$C$68*D12) -> 2.4157209 | E21: =Externo!E46/(Externo!E34+Externo!E36+Supuestos!$C$68*E12) -> 3.1615157 | F21: =Externo!F46/(Externo!F34+Externo!F36+Supuestos!$C$68*F12) -> 3.4779399 | G21: =Externo!G46/(Externo!G34+Externo!G36+Supuestos!$C$68*G12) -> 3.7187705 | H21: =Externo!H46/(Externo!H34+Externo!H36+Supuestos!$C$68*H12) -> 3.119267 | I21: =Externo!I46/(Externo!I34+Externo!I36+Supuestos!$C$68*I12) -> 2.9757398 | J21: =Externo!J46/(Externo!J34+Externo!J36+Supuestos!$C$68*J12) -> 2.3668972 | K21: =Externo!K46/(Externo!K34+Externo!K36+Supuestos!$C$68*K12) -> 1.6941803 | ... M21: =Externo!M46/(Externo!M34+Externo!M36+Supuestos!$C$68*M12) -> 1.5086699 | N21: Regla Greenspan-Guidotti: >1
A22: Ajuste cambiario endógeno
A23: Brecha externa cerrada vía tipo de cambio | B23: USD mm M | C23: =Externo!C44 -> 0 | D23: =Externo!D44 -> 0 | E23: =Externo!E44 -> 0 | F23: =Externo!F44 -> 0 | G23: =Externo!G44 -> 0 | H23: =Externo!H44 -> 0 | I23: =Externo!I44 -> 0 | J23: =Externo!J44 -> 0 | ... M23: =Externo!M44 -> 0.42298995
A24: Depreciación de ajuste | B24: % | C24: =Externo!C45 -> 0 | D24: =Externo!D45 -> 0 | E24: =Externo!E45 -> 0 | F24: =Externo!F45 -> 0 | G24: =Externo!G45 -> 0 | H24: =Externo!H45 -> 0 | I24: =Externo!I45 -> 0 | J24: =Externo!J45 -> 0 | ... M24: =Externo!M45 -> 0.074858337
A25: Tipo de cambio fin de año | B25: Bs/USD | C25: =Fiscal_Deuda!C9 -> 6.96 | D25: =Fiscal_Deuda!D9 -> 11.8 | E25: =Fiscal_Deuda!E9 -> 12.755073 | F25: =Fiscal_Deuda!F9 -> 13.318641 | G25: =Fiscal_Deuda!G9 -> 13.662347 | H25: =Fiscal_Deuda!H9 -> 14.022937 | I25: =Fiscal_Deuda!I9 -> 14.255967 | J25: =Fiscal_Deuda!J9 -> 14.49287 | ... M25: =Fiscal_Deuda!M9 -> 19.681527

Sheet Escenarios
A1: Comparación de escenarios (salida de modelo.py)
A2: Valores calculados por el motor en Python con las mismas ecuaciones que las hojas de fórmulas; seleccionando el escenario en Portada!C6 las hojas vivas reproducen estas cifras.
A4: Deuda pública / PIB
A5: Escenario | C5: 2025 | D5: 2026 | E5: 2027 | F5: 2028 | G5: 2029 | H5: 2030 | I5: 2031 | J5: 2032 | K5: 2033 | L5: 2034 | M5: 2035
A6: Base | C6: 0.83307586 | D6: 1.0019902 | E6: 0.99288556 | F6: 0.97024731 | G6: 0.9403403 | H6: 0.91458487 | I6: 0.89207427 | J6: 0.87069633 | K6: 0.8544833 | L6: 0.85050633 | M6: 0.84057989
A7: Réplica FMI (TCR que replica su sendero) | C7: 0.83307586 | D7: 1.0019902 | E7: 0.97500282 | F7: 0.93617352 | G7: 0.89200358 | H7: 0.86804634 | I7: 0.85914014 | J7: 0.8479954 | K7: 0.83190087 | L7: 0.81599251 | M7: 0.80193343
A8: Reversión de metales preciosos | C8: 0.83307586 | D8: 1.0019902 | E8: 1.0138629 | F8: 1.0190093 | G8: 1.0042723 | H8: 0.99676492 | I8: 0.97891084 | J8: 0.96252373 | K8: 0.95087483 | L8: 0.93928053 | M8: 0.92724415
A9: Declive acelerado del gas + petróleo caro | C9: 0.83307586 | D9: 1.0019902 | E9: 1.0061213 | F9: 0.99415682 | G9: 0.9755183 | H9: 0.96110268 | I9: 0.95952915 | J9: 0.96147762 | K9: 0.95916575 | L9: 0.95458252 | M9: 0.95101252
A10: Desliz fiscal (-2 pp PIB) | C10: 0.83307586 | D10: 1.0019902 | E10: 1.0128856 | F10: 1.0098739 | G10: 0.9997397 | H10: 0.99553124 | I10: 1.0097181 | J10: 1.020999 | K10: 1.0255247 | L10: 1.0295676 | M10: 1.0353679
A11: Salida de capitales / menos IED | C11: 0.83307586 | D11: 1.0019902 | E11: 0.99288556 | F11: 0.97024731 | G11: 0.9403403 | H11: 0.93033647 | I11: 0.92097728 | J11: 0.90338386 | K11: 0.88558394 | L11: 0.86959059 | M11: 0.85469961
A12: Combinado (tormenta) | C12: 0.83307586 | D12: 1.0019902 | E12: 1.0525349 | F12: 1.0746487 | G12: 1.0761621 | H12: 1.0820374 | I12: 1.0756073 | J12: 1.071005 | K12: 1.0716037 | L12: 1.0721004 | M12: 1.0717288
A13: Base + reperfilamiento bilateral/bonos | C13: 0.83307586 | D13: 1.0019902 | E13: 0.99317674 | F13: 0.97085891 | G13: 0.94105665 | H13: 0.91559724 | I13: 0.8932276 | J13: 0.87191645 | K13: 0.85212807 | L13: 0.85321392 | M13: 0.85039708
A15: Reservas brutas (USD mm M)
A16: Escenario | C16: 2025 | D16: 2026 | E16: 2027 | F16: 2028 | G16: 2029 | H16: 2030 | I16: 2031 | J16: 2032 | K16: 2033 | L16: 2034 | M16: 2035
A17: Base | C17: 3.81 | D17: 5.1938 | E17: 6.5742787 | F17: 7.5194788 | G17: 8.0313368 | H17: 7.6855808 | I17: 7.1117231 | J17: 6.0501411 | K17: 4.6864741 | L17: 4.0619088 | M17: 4.2532437
A18: Réplica FMI (TCR que replica su sendero) | C18: 3.81 | D18: 5.1938 | E18: 6.2783785 | F18: 6.5965685 | G18: 6.1021333 | H18: 4.6995587 | I18: 3.9277729 | J18: 3.9696858 | K18: 4.1930311 | L18: 4.3589068 | M18: 4.4379223
A19: Reversión de metales preciosos | C19: 3.81 | D19: 5.1938 | E19: 3.5845949 | F19: 3.3343073 | G19: 3.3092478 | H19: 3.1928951 | I19: 3.4117045 | J19: 3.489376 | K19: 3.4871111 | L19: 3.5688784 | M19: 3.6621822
A20: Declive acelerado del gas + petróleo caro | C20: 3.81 | D20: 5.1938 | E20: 5.8689987 | F20: 6.2074928 | G20: 6.0333425 | H20: 4.9450403 | I20: 4.144657 | J20: 3.9570115 | K20: 4.110189 | L20: 4.3071393 | M20: 4.4100796
A21: Desliz fiscal (-2 pp PIB) | C21: 3.81 | D21: 5.1938 | E21: 6.247299 | F21: 6.5710968 | G21: 6.1393298 | H21: 4.6120231 | I21: 3.7817916 | J21: 3.8617458 | K21: 4.1266309 | L21: 4.3070985 | M21: 4.3864297
A22: Salida de capitales / menos IED | C22: 3.81 | D22: 5.1938 | E22: 5.5242787 | F22: 5.3194788 | G22: 4.5813368 | H22: 3.6142734 | I22: 3.5576293 | J22: 3.7590696 | K22: 3.8666512 | L22: 3.9637036 | M22: 4.050352
A23: Combinado (tormenta) | C23: 3.81 | D23: 5.1938 | E23: 3.66177 | F23: 3.1856333 | G23: 3.1366046 | H23: 3.0651593 | I23: 3.3132474 | J23: 3.3943697 | K23: 3.3898164 | L23: 3.4744116 | M23: 3.5748188
A24: Base + reperfilamiento bilateral/bonos | C24: 3.81 | D24: 5.1938 | E24: 6.8742787 | F24: 8.1238788 | G24: 8.8034968 | H24: 8.8951008 | I24: 8.4536431 | J24: 7.0140611 | K24: 5.0150006 | L24: 3.9368622 | M24: 3.9314846
A26: Tipo de cambio fin de año (Bs/USD)
A27: Escenario | C27: 2025 | D27: 2026 | E27: 2027 | F27: 2028 | G27: 2029 | H27: 2030 | I27: 2031 | J27: 2032 | K27: 2033 | L27: 2034 | M27: 2035
A28: Base | C28: 6.96 | D28: 11.8 | E28: 12.755073 | F28: 13.318641 | G28: 13.662347 | H28: 14.022937 | I28: 14.255967 | J28: 14.49287 | K28: 15.344946 | L28: 18.011499 | M28: 19.681527
A29: Réplica FMI (TCR que replica su sendero) | C29: 6.96 | D29: 11.8 | E29: 12.24487 | F29: 12.279678 | G29: 12.102889 | H29: 12.42232 | I29: 14.554204 | J29: 16.273045 | K29: 17.175008 | L29: 17.842993 | M29: 18.717296
A30: Reversión de metales preciosos | C30: 6.96 | D30: 11.8 | E30: 13.290985 | F30: 15.148525 | G30: 16.816337 | H30: 18.960942 | I30: 19.781263 | J30: 20.710603 | K30: 22.121202 | L30: 23.382277 | M30: 24.549913
A31: Declive acelerado del gas + petróleo caro | C31: 6.96 | D31: 11.8 | E31: 12.755073 | F31: 13.318641 | G31: 13.662347 | H31: 14.022937 | I31: 15.718983 | J31: 17.869556 | K31: 19.253589 | L31: 20.033583 | M31: 20.931818
A32: Desliz fiscal (-2 pp PIB) | C32: 6.96 | D32: 11.8 | E32: 12.755073 | F32: 13.318641 | G32: 13.662347 | H32: 14.291816 | I32: 17.34444 | J32: 19.963843 | K32: 21.584901 | L32: 22.974925 | M32: 24.72147
A33: Salida de capitales / menos IED | C33: 6.96 | D33: 11.8 | E33: 12.755073 | F33: 13.318641 | G33: 13.662347 | H33: 15.851702 | I33: 17.8496 | J33: 18.894728 | K33: 19.815655 | L33: 20.755403 | M33: 21.78308
A34: Combinado (tormenta) | C34: 6.96 | D34: 11.8 | E34: 13.217615 | F34: 15.811273 | G34: 18.232589 | H34: 20.919917 | I34: 22.041178 | J34: 23.355176 | K34: 25.30325 | L34: 27.130909 | M34: 28.865853
A35: Base + reperfilamiento bilateral/bonos | C35: 6.96 | D35: 11.8 | E35: 12.755073 | F35: 13.318641 | G35: 13.662347 | H35: 14.022937 | I35: 14.255967 | J35: 14.49287 | K35: 14.73371 | L35: 17.869112 | M35: 20.561981
A37: NBF / PIB
A38: Escenario | C38: 2025 | D38: 2026 | E38: 2027 | F38: 2028 | G38: 2029 | H38: 2030 | I38: 2031 | J38: 2032 | K38: 2033 | L38: 2034 | M38: 2035
A39: Base | D39: 0.21292044 | E39: 0.20060846 | F39: 0.1782545 | G39: 0.16097801 | H39: 0.16022901 | I39: 0.15400353 | J39: 0.15124562 | K39: 0.14851808 | L39: 0.14308202 | M39: 0.14293998
A40: Réplica FMI (TCR que replica su sendero) | D40: 0.21292044 | E40: 0.20010989 | F40: 0.17636604 | G40: 0.15795111 | H40: 0.1559415 | I40: 0.1446035 | J40: 0.14128054 | K40: 0.14088447 | L40: 0.14006043 | M40: 0.13882148
A41: Reversión de metales preciosos | D41: 0.21292044 | E41: 0.20459806 | F41: 0.18232613 | G41: 0.16484293 | H41: 0.16446321 | I41: 0.16007196 | J41: 0.15752926 | K41: 0.15627039 | L41: 0.15600893 | M41: 0.1562029
A42: Declive acelerado del gas + petróleo caro | D42: 0.21292044 | E42: 0.2138442 | F42: 0.19249804 | G42: 0.17846493 | H42: 0.18059824 | I42: 0.17302744 | J42: 0.17125938 | K42: 0.17397078 | L42: 0.1766926 | M42: 0.17850334
A43: Desliz fiscal (-2 pp PIB) | D43: 0.21292044 | E43: 0.22060846 | F43: 0.20327527 | G43: 0.19105693 | H43: 0.19428222 | I43: 0.18510063 | J43: 0.18581604 | K43: 0.19000043 | L43: 0.19335467 | M43: 0.19623634
A44: Salida de capitales / menos IED | D44: 0.21292044 | E44: 0.20060846 | F44: 0.1782545 | G44: 0.16097801 | H44: 0.15543064 | I44: 0.1481809 | J44: 0.1463434 | K44: 0.14511312 | L44: 0.14381568 | M44: 0.14283608
A45: Combinado (tormenta) | D45: 0.21292044 | E45: 0.21448234 | F45: 0.20021227 | G45: 0.1849223 | H45: 0.18764904 | I45: 0.18577251 | J45: 0.18561535 | K45: 0.18669285 | L45: 0.18882384 | M45: 0.19155089
A46: Base + reperfilamiento bilateral/bonos | D46: 0.21292044 | E46: 0.19312219 | F46: 0.1690121 | G46: 0.15335293 | H46: 0.14593226 | I46: 0.14425764 | J46: 0.15120616 | K46: 0.15168947 | L46: 0.14347154 | M46: 0.14898273
A48: Cuenta corriente / PIB
A49: Escenario | C49: 2025 | D49: 2026 | E49: 2027 | F49: 2028 | G49: 2029 | H49: 2030 | I49: 2031 | J49: 2032 | K49: 2033 | L49: 2034 | M49: 2035
A50: Base | C50: -0.020970545 | D50: 0.013354343 | E50: 0.011291266 | F50: -0.0053408774 | G50: -0.015467896 | H50: -0.023081862 | I50: -0.029568877 | J50: -0.035824638 | K50: -0.037161667 | L50: -0.022139636 | M50: -0.0057590364
A51: Réplica FMI (TCR que replica su sendero) | C51: -0.020970545 | D51: 0.013354343 | E51: 0.0038261123 | F51: -0.019289022 | G51: -0.035030992 | H51: -0.04111077 | I51: -0.030672749 | J51: -0.013552308 | K51: -0.0069255513 | L51: -0.0071025646 | M51: -0.0075517164
A52: Reversión de metales preciosos | C52: -0.020970545 | D52: 0.013354343 | E52: -0.039306037 | F52: -0.038066104 | G52: -0.031607033 | H52: -0.021580819 | I52: -0.016179206 | J52: -0.016632337 | K52: -0.014349393 | L52: -0.01107272 | M52: -0.0093213498
A53: Declive acelerado del gas + petróleo caro | C53: -0.020970545 | D53: 0.013354343 | E53: -0.0063084655 | F53: -0.020016343 | G53: -0.03134941 | H53: -0.039471296 | I53: -0.034947516 | J53: -0.019916647 | K53: -0.0092579806 | L53: -0.0073089961 | M53: -0.0079873284
A54: Desliz fiscal (-2 pp PIB) | C54: -0.020970545 | D54: 0.013354343 | E54: 0.0031317324 | F54: -0.020371825 | G54: -0.037313396 | H54: -0.049327713 | I54: -0.036604152 | J54: -0.015054953 | K54: -0.0073050528 | L54: -0.0082994101 | M54: -0.0093330527
A55: Salida de capitales / menos IED | C55: -0.020970545 | D55: 0.013354343 | E55: 0.011291266 | F55: -0.0053408774 | G55: -0.015467896 | H55: -0.0082901813 | I55: 0.0096705254 | J55: 0.018201081 | K55: 0.019108261 | L55: 0.019161832 | M55: 0.019444382
A56: Combinado (tormenta) | C56: -0.020970545 | D56: 0.013354343 | E56: -0.030523225 | F56: -0.027912164 | G56: -0.015211671 | H56: -0.0020015277 | I56: 0.0034021367 | J56: 0.0015540342 | K56: 0.0033632815 | L56: 0.0067588911 | M56: 0.0083903152
A57: Base + reperfilamiento bilateral/bonos | C57: -0.020970545 | D57: 0.013354343 | E57: 0.011291266 | F57: -0.005718222 | G57: -0.016214272 | H57: -0.024023009 | I57: -0.0309944 | J57: -0.037388699 | K57: -0.042915382 | L57: -0.026441456 | M57: -0.00017251104
A59: Servicio deuda externa / export.
A60: Escenario | C60: 2025 | D60: 2026 | E60: 2027 | F60: 2028 | G60: 2029 | H60: 2030 | I60: 2031 | J60: 2032 | K60: 2033 | L60: 2034 | M60: 2035
A61: Base | D61: 0.12192647 | E61: 0.13860018 | F61: 0.15167695 | G61: 0.15110217 | H61: 0.17023743 | I61: 0.15770893 | J61: 0.16266674 | K61: 0.17045589 | L61: 0.16911246 | M61: 0.16782269
A62: Réplica FMI (TCR que replica su sendero) | D62: 0.12192647 | E62: 0.13883289 | F62: 0.15220901 | G62: 0.15191088 | H62: 0.17117563 | I62: 0.15860069 | J62: 0.163021 | K62: 0.17040891 | L62: 0.16907898 | M62: 0.16839284
A63: Reversión de metales preciosos | D63: 0.12192647 | E63: 0.16973454 | F63: 0.18527436 | G63: 0.18437794 | H63: 0.20736886 | I63: 0.19149357 | J63: 0.19728896 | K63: 0.20644972 | L63: 0.20458737 | M63: 0.20347386
A64: Declive acelerado del gas + petróleo caro | D64: 0.12192647 | E64: 0.13977687 | F64: 0.15183884 | G64: 0.15208971 | H64: 0.17194448 | I64: 0.1596976 | J64: 0.16458147 | K64: 0.17210653 | L64: 0.17073639 | M64: 0.17004752
A65: Desliz fiscal (-2 pp PIB) | D65: 0.12192647 | E65: 0.13860018 | F65: 0.15167695 | G65: 0.15110217 | H65: 0.17023743 | I65: 0.15763522 | J65: 0.16180143 | K65: 0.16892662 | L65: 0.16743925 | M65: 0.16658924
A66: Salida de capitales / menos IED | D66: 0.12192647 | E66: 0.13860018 | F66: 0.15167695 | G66: 0.15110217 | H66: 0.17023743 | I66: 0.15720898 | J66: 0.16169005 | K66: 0.16921829 | L66: 0.16788912 | M66: 0.16713276
A67: Combinado (tormenta) | D67: 0.12192647 | E67: 0.16136691 | F67: 0.1767755 | G67: 0.17590124 | H67: 0.19777491 | I67: 0.1827253 | J67: 0.18832518 | K67: 0.19707267 | L67: 0.19523531 | M67: 0.19407242
A68: Base + reperfilamiento bilateral/bonos | D68: 0.12192647 | E68: 0.11605107 | F68: 0.1283288 | G68: 0.13838179 | H68: 0.13756492 | I68: 0.14799923 | J68: 0.18987038 | K68: 0.19745327 | L68: 0.18631216 | M68: 0.20264419
A70: Depreciación de ajuste endógena
A71: Escenario | C71: 2025 | D71: 2026 | E71: 2027 | F71: 2028 | G71: 2029 | H71: 2030 | I71: 2031 | J71: 2032 | K71: 2033 | L71: 2034 | M71: 2035
A72: Base | D72: 0 | E72: 0 | F72: 0 | G72: 0 | H72: 0 | I72: 0 | J72: 0 | K72: 0.041485577 | L72: 0.15458731 | M72: 0.074858337
A73: Réplica FMI (TCR que replica su sendero) | D73: 0 | E73: 0 | F73: 0 | G73: 0 | H73: 0 | I73: 0.15246581 | J73: 0.099822605 | K73: 0.038174675 | L73: 0.02191096 | M73: 0.031852661
A74: Reversión de metales preciosos | D74: 0 | E74: 0.0420156 | F74: 0.091531411 | G74: 0.082170299 | H74: 0.098537406 | I74: 0.026210387 | J74: 0.029866706 | K74: 0.050650509 | L74: 0.039729492 | M74: 0.032774363
A75: Declive acelerado del gas + petróleo caro | D75: 0 | E75: 0 | F75: 0 | G75: 0 | H75: 0 | I75: 0.10262476 | J75: 0.11823121 | K75: 0.059839837 | L75: 0.023503238 | M75: 0.02775741
A76: Desliz fiscal (-2 pp PIB) | D76: 0 | E76: 0 | F76: 0 | G76: 0 | H76: 0.019174191 | I76: 0.19375489 | J76: 0.13220788 | K76: 0.063526211 | L76: 0.04699917 | M76: 0.058430854
A77: Salida de capitales / menos IED | D77: 0 | E77: 0 | F77: 0 | G77: 0 | H77: 0.13041239 | I77: 0.10763043 | J77: 0.041248681 | K77: 0.031596982 | L77: 0.030303179 | M77: 0.032358206
A78: Combinado (tormenta) | D78: 0 | E78: 0.036263315 | F78: 0.14561002 | G78: 0.12412884 | H78: 0.11788713 | I78: 0.036375497 | J78: 0.042294943 | K78: 0.065701193 | L78: 0.05470339 | M78: 0.046555686
A79: Base + reperfilamiento bilateral/bonos | D79: 0 | E79: 0 | F79: 0 | G79: 0 | H79: 0 | I79: 0 | J79: 0 | K79: 0 | L79: 0.19298001 | M79: 0.1318901

Sheet Estocastico
A1: Simulación estocástica (Monte Carlo, 5.000 sendas, escenario base)
A2: Choques correlacionados a precios de metales preciosos/base, petróleo y crecimiento (AR(1) en niveles), más choques a volumen de gas, precios agro, flujos privados, balance primario y tasa interna. A diferencia del fan chart estándar del FMI (VAR sobre variables fiscales históricas), aquí los choques externos pasan por la balanza de pagos, las reservas y el tipo de cambio antes de llegar a la deuda.
A4: Deuda pública / PIB
A5: Percentil | C5: 2025 | D5: 2026 | E5: 2027 | F5: 2028 | G5: 2029 | H5: 2030 | I5: 2031 | J5: 2032 | K5: 2033 | L5: 2034 | M5: 2035
A6: P10 | C6: 0.83307586 | D6: 1.0019902 | E6: 0.969954 | F6: 0.9307542 | G6: 0.88670311 | H6: 0.85103223 | I6: 0.81994754 | J6: 0.79198715 | K6: 0.76684835 | L6: 0.74343752 | M6: 0.72293505
A7: P25 | C7: 0.83307586 | D7: 1.0019902 | E7: 0.98061459 | F7: 0.94943104 | G7: 0.91187223 | H7: 0.88231804 | I7: 0.85558461 | J7: 0.83214345 | K7: 0.81087718 | L7: 0.79424008 | M7: 0.77776569
A8: P50 | C8: 0.83307586 | D8: 1.0019902 | E8: 0.99269279 | F8: 0.97018377 | G8: 0.94202674 | H8: 0.91827138 | I8: 0.89913573 | J8: 0.88165808 | K8: 0.86539202 | L8: 0.85118766 | M8: 0.83727666
A9: P75 | C9: 0.83307586 | D9: 1.0019902 | E9: 1.0059088 | F9: 0.99266975 | G9: 0.97219353 | H9: 0.95807566 | I9: 0.94625606 | J9: 0.93437599 | K9: 0.92346171 | L9: 0.91227114 | M9: 0.90281165
A10: P90 | C10: 0.83307586 | D10: 1.0019902 | E10: 1.0169189 | F10: 1.013699 | G10: 1.0018285 | H10: 0.99650625 | I10: 0.99055385 | J10: 0.98284763 | K10: 0.97481995 | L10: 0.96956637 | M10: 0.96203996
A12: Reservas brutas (USD mm M)
A13: Percentil | C13: 2025 | D13: 2026 | E13: 2027 | F13: 2028 | G13: 2029 | H13: 2030 | I13: 2031 | J13: 2032 | K13: 2033 | L13: 2034 | M13: 2035
A14: P10 | C14: 3.81 | D14: 5.1938 | E14: 4.5556938 | F14: 4.1487609 | G14: 3.8280173 | H14: 3.4187388 | I14: 3.3688401 | J14: 3.4353863 | K14: 3.4875564 | L14: 3.4978685 | M14: 3.6158289
A15: P25 | C15: 3.81 | D15: 5.1938 | E15: 5.4197886 | F15: 5.5925891 | G15: 5.4130891 | H15: 4.7045618 | I15: 4.4993832 | J15: 4.5521921 | K15: 4.5252047 | L15: 4.5884425 | M15: 4.7039674
A16: P50 | C16: 3.81 | D16: 5.1938 | E16: 6.5292202 | F16: 7.5071942 | G16: 8.0395387 | H16: 7.8488425 | I16: 7.7276693 | J16: 7.5796219 | K16: 7.5545341 | L16: 7.6429529 | M16: 7.7211738
A17: P75 | C17: 3.81 | D17: 5.1938 | E17: 7.7514631 | F17: 9.6470604 | G17: 11.262231 | H17: 12.025993 | I17: 12.659428 | J17: 12.913977 | K17: 13.098528 | L17: 13.246036 | M17: 13.688943
A18: P90 | C18: 3.81 | D18: 5.1938 | E18: 8.8813281 | F18: 11.75286 | G18: 14.499728 | H18: 16.423121 | I18: 17.848025 | J18: 19.016716 | K18: 19.856709 | L18: 20.362905 | M18: 21.159997
A20: Tipo de cambio (Bs/USD)
A21: Percentil | C21: 2025 | D21: 2026 | E21: 2027 | F21: 2028 | G21: 2029 | H21: 2030 | I21: 2031 | J21: 2032 | K21: 2033 | L21: 2034 | M21: 2035
A22: P10 | C22: 6.96 | D22: 11.8 | E22: 12.755073 | F22: 13.318641 | G22: 13.662347 | H22: 14.022937 | I22: 14.255967 | J22: 14.49287 | K22: 14.73371 | L22: 14.978551 | M22: 15.227462
A23: P25 | C23: 6.96 | D23: 11.8 | E23: 12.755073 | F23: 13.318641 | G23: 13.662347 | H23: 14.022937 | I23: 14.255967 | J23: 14.49287 | K23: 14.73371 | L23: 14.978551 | M23: 15.227462
A24: P50 | C24: 6.96 | D24: 11.8 | E24: 12.755073 | F24: 13.318641 | G24: 13.662347 | H24: 14.022937 | I24: 14.255967 | J24: 14.49287 | K24: 15.344898 | L24: 17.304154 | M24: 18.871481
A25: P75 | C25: 6.96 | D25: 11.8 | E25: 12.755073 | F25: 13.318641 | G25: 13.662347 | H25: 14.65686 | I25: 16.53629 | J25: 18.289759 | K25: 19.909396 | L25: 21.60045 | M25: 23.046739
A26: P90 | C26: 6.96 | D26: 11.8 | E26: 12.755073 | F26: 13.473366 | G26: 15.283582 | H26: 17.722106 | I26: 19.829814 | J26: 21.887042 | K26: 23.531009 | L26: 24.895917 | M26: 26.444437
A28: NBF / PIB
A29: Percentil | C29: 2025 | D29: 2026 | E29: 2027 | F29: 2028 | G29: 2029 | H29: 2030 | I29: 2031 | J29: 2032 | K29: 2033 | L29: 2034 | M29: 2035
A30: P10 | D30: 0.21292044 | E30: 0.18689522 | F30: 0.15962971 | G30: 0.139107 | H30: 0.13595343 | I30: 0.12722242 | J30: 0.12221999 | K30: 0.11978628 | L30: 0.11710185 | M30: 0.11474207
A31: P25 | D31: 0.21292044 | E31: 0.19322106 | F31: 0.16774514 | G31: 0.14824162 | H31: 0.14620578 | I31: 0.13848958 | J31: 0.13448974 | K31: 0.13219924 | L31: 0.12999238 | M31: 0.12820452
A32: P50 | D32: 0.21292044 | E32: 0.20031095 | F32: 0.17711188 | G32: 0.15862624 | H32: 0.15740227 | I32: 0.15083279 | J32: 0.14700782 | K32: 0.14569711 | L32: 0.14419715 | M32: 0.1431592
A33: P75 | D33: 0.21292044 | E33: 0.2074753 | F33: 0.1869278 | G33: 0.17024058 | H33: 0.1692912 | I33: 0.1634985 | J33: 0.16060231 | K33: 0.15974072 | L33: 0.15906274 | M33: 0.15833632
A34: P90 | D34: 0.21292044 | E34: 0.21344516 | F34: 0.19516569 | G34: 0.18032703 | H34: 0.18073907 | I34: 0.17565066 | J34: 0.17343412 | K34: 0.17268653 | L34: 0.17238813 | M34: 0.17332943
A36: Probabilidades (sobre 5.000 sendas)
A37: Deuda/PIB 2030 > 100% | C37: 0.092
A38: Deuda/PIB 2030 > deuda/PIB 2026 (no baja) | C38: 0.0872
A39: Deuda/PIB 2035 > 70% (umbral MAC) | C39: 0.9366
A40: NBF/PIB > 15% en 2030 | C40: 0.6704
A41: Reservas < 3 meses de import. algún año 2027-2031 | C41: 0.0564
A42: Depreciación de ajuste > 10% algún año 2027-2031 | C42: 0.2836
A43: Deuda/PIB 2029 > 89,2% (proyección FMI) | C43: 0.8738

Sheet FMI_vs_Modelo
A1: Qué agrega este DSA frente al marco estándar del FMI
A3: Dimensión | B3: DSA estándar (MAC SRDSF / staff report) | C3: Este modelo
A4: Tipo de cambio | B4: Senda exógena; choque cambiario genérico como prueba de tensión. | C4: Endógeno: la brecha de balanza de pagos frente al piso/nivel cómodo de reservas se cierra con depreciación, que revalúa la deuda en USD, sube el deflactor y resta crecimiento.
A5: Exportaciones | B5: Agregadas; choques de commodities como escenario puntual. | C5: Desagregadas por motor (metales preciosos, metales base, gas, agro, resto) con precio y volumen propios; gas con declinación de campos e indexación rezagada al petróleo.
A6: Vínculo fiscal-externo | B6: Implícito. | C6: Explícito: renta hidrocarburífera y minera dependen del valor exportado y del tipo de cambio; el subsidio a combustibles depende del precio del petróleo y del tipo de cambio; el desliz fiscal aumenta importaciones (déficits gemelos).
A7: Reservas | B7: Se reportan; no retroalimentan la deuda. | C7: Variable de estado: acumulan cuenta corriente + IED + financiamiento oficial + FMI + flujos privados + valuación del oro. Determinan el ajuste cambiario.
A8: Abanico estocástico | B8: Choques históricos a crecimiento, tasas, tipo de cambio y balance primario. | C8: Choques a precios de commodities correlacionados con persistencia, que atraviesan la balanza de pagos antes de llegar a la deuda.
A9: Perímetro de deuda | B9: SPNF bruto. | C9: SPNF bruto y neto de tenencias del BCB (≈55% de la deuda interna), más composición por moneda.
A10: Indicadores externos | B10: Separados en DSA externo. | C10: Integrados: deuda externa total/PIB y /export., servicio/export., reservas en meses de importación, Greenspan-Guidotti.
A11: Supuesto implícito de TCR | B11: No se explicita. | C11: Escenario 'Réplica FMI' calibra cuánta apreciación real 2027-29 se necesita para que, con los déficits del programa, la deuda llegue a 89,2% del PIB en 2029. Ese mismo escenario muestra el costo externo de esa apreciación.
A13: Limitaciones
A14: • Datos de balanza de pagos 2026 son estimaciones a partir de comercio exterior ene-ago (INE) y del WEO oct-2026; no hay BoP oficial 2026.
A15: • El cronograma de amortizaciones externas es una aproximación; no se tuvo acceso al informe de deuda externa del BCB ni al staff report completo del FMI.
A16: • La regla cambiaria es asimétrica (sólo deprecia ante caída de reservas); con reservas abundantes el modelo acumula en vez de apreciar.
A17: • No modela explícitamente el sistema financiero ni la dolarización de depósitos; los pasivos contingentes entran como choque de stock.
A18: • El auge exportador de 2026 mezcla precios (plata, oro) y formalización de exportaciones antes informales tras la flotación; separar ambos es clave y no está resuelto.
A19: • Las elasticidades son supuestos calibrados, no estimaciones econométricas.

Sheet Fuentes
A1: Fuentes
A3: Dato | B3: URL
A4: FMI, acuerdo a nivel técnico SAF (29-jul-2026) | B4: https://www.imf.org/en/news/articles/2026/07/29/pr26268-bolivia-imf-reaches-staff-level-agreement-on-an-extended-fund-facility-arrangement
A5: Aprobación del Directorio FMI, 2-oct-2026 (USD 1.900 M; USD 214 M inmediatos) | B5: https://www.riotimesonline.com/bolivia-imf-loan-approved-214-million-expats-2026/
A6: Informe técnico FMI: deuda 100,2% PIB 2026; déficit 11,4%→9,2%→6,7% | B6: https://fmbolivia.com.bo/nacional/deuda-publica-de-bolivia-llegaria-al-100-2-del-pib-en-2026-segun-informe-tecnico-del-fmi-21327
A7: Acuerdo FMI: ajuste 8,5% PIB, deuda 89,2% en 2029 | B7: https://fmlapaz.bo/fmi-hace-publico-el-acuerdo-con-bolivia-us-1-900-millones-ajuste-del-85-del-pib-y-eliminacion-del-subsidio-a-los-combustibles-en-2027/
A8: FMI WEO oct-2026: PIB -3,0%/-1,5%; CC +1,6%/+1,0% PIB | B8: https://www.vision360.bo/noticias/2026/10/13/72357-fmi-bolivia-sera-la-unica-economia-de-sudamerica-que-se-contraera-en-2026-y-2027
A9: Deuda externa pública USD 14.117 M a sep-2026 (BCB) | B9: https://unitel.bo/noticias/agencias/deuda-externa-publica-de-bolivia-llega-a-14117-millones-de-dolares-a-septiembre-de-2026-OC24040790
A10: BCB, Reporte de Balanza de Pagos 2025 | B10: https://www.bcb.gob.bo/webdocs/publicacionesbcb/2026/03/31/BOP%202025%20(4).pdf
A11: BCB, Resumen de cifras BoP 2025 (CC -1.218 M; bienes +334 M) | B11: https://www.bcb.gob.bo/webdocs/publicacionesbcb/2026/02/03/Resumen%20de%20cifras%20(WEB).pdf
A12: INE vía eju.tv: export. ene-ago 2026 USD 8.987 M; saldo comercial +2.029 M | B12: https://eju.tv/2026/10/bolivia-registro-un-saldo-comercial-superior-a-us-2-000-millones-entre-enero-y-agosto-de-este-ano-segun-el-ine/
A13: IBCE: exportaciones a junio 2026 | B13: https://www.ibce.org.bo//images/ibcecifras_documentos/Cifras_1.441_Exportaciones_junio_2026_1786634430.pdf
A14: Export. de gas 2025: USD 1.077 M (-33%) | B14: https://unitel.bo/noticias/economia/bolivia-registro-una-caida-cercana-a-us-540-millones-en-la-exportacion-de-gas-en-2025-segun-el-ine-PL19126328
... A23: FinDev Lab (abr-2026): DSA independiente con reperfilamiento | B23: http://findevlab.org/wp-content/uploads/2026/04/FDL_Policy-Note-34_A-New-Day-for-Bolivia_The-Anatomy-of-a-Crisis-and-the-Options-Ahead.pdf
A25: Nota: varias cifras provienen de prensa que cita fuentes oficiales; el acceso directo a imf.org y bcb.gob.bo no estuvo disponible al construir el modelo. Verificar contra los documentos originales antes de publicar.
